{
    "pos_tag_counting_response_en_en_6": {
        "NOUN": {
            "mean": 0.2155,
            "std_dev": 0.0176,
            "cv": 8.1552
        },
        "PROPN": {
            "mean": 0.0695,
            "std_dev": 0.0161,
            "cv": 23.2055
        },
        "VERB": {
            "mean": 0.0908,
            "std_dev": 0.013,
            "cv": 14.2674
        },
        "AUX": {
            "mean": 0.0197,
            "std_dev": 0.0095,
            "cv": 48.2577
        },
        "ADJ": {
            "mean": 0.0935,
            "std_dev": 0.0147,
            "cv": 15.7563
        },
        "ADV": {
            "mean": 0.0369,
            "std_dev": 0.0129,
            "cv": 35.0648
        },
        "PRON": {
            "mean": 0.0866,
            "std_dev": 0.0185,
            "cv": 21.3446
        },
        "NUM": {
            "mean": 0.0,
            "std_dev": 0.0,
            "cv": 0
        },
        "DET": {
            "mean": 0.0749,
            "std_dev": 0.0178,
            "cv": 23.7464
        },
        "PART": {
            "mean": 0.018,
            "std_dev": 0.012,
            "cv": 66.5045
        },
        "CCONJ": {
            "mean": 0.0527,
            "std_dev": 0.0113,
            "cv": 21.5299
        },
        "SCONJ": {
            "mean": 0.0101,
            "std_dev": 0.0071,
            "cv": 70.5197
        },
        "ADP": {
            "mean": 0.1384,
            "std_dev": 0.0177,
            "cv": 12.7683
        },
        "INTJ": {
            "mean": 0.0,
            "std_dev": 0.0,
            "cv": 0
        },
        "PUNCT": {
            "mean": 0.0934,
            "std_dev": 0.0142,
            "cv": 15.1906
        },
        "X": {
            "mean": 0.0,
            "std_dev": 0.0,
            "cv": 0
        },
        "NON-ZH": {
            "mean": 0.0,
            "std_dev": 0.0,
            "cv": 0
        }
    }
}