<?xml version='1.0' encoding='UTF-8'?>
<responses prompt_type="en" response_type="zh">
  <response id="p8-r1">在美国最高法院的檐柱上雕刻孔子的形象，反映了西方法律体系对古代哲学和智慧传统的重视。孔子被视为道德和伦理的象征，他的思想强调社会秩序、正义和人际关系的重要性，这与法律的基本原则相契合。通过这种雕刻，最高法院展示了法律不仅仅是规则的集合，也是深厚的道德与伦理思想的延伸，表明它在很大程度上受到了包括儒家思想在内的全球智慧的影响。</response>
  <response id="p8-r2">美国最高法院的外立面上刻有孔子的雕像，反映了孔子作为古代中国重要哲学家和思想家的影响。孔子提倡的伦理道德、正义与社会和谐与西方法律和治理中的许多原则相呼应。他的思想强调个人在社会中的责任和道德义务，这与美国法律体系中对公民责任和社会公正的重视相符。因此，孔子的雕像不仅代表了对古代智慧的尊重，也象征着法律与道德交织的重要性。</response>
  <response id="p8-r3">美国最高法院的檐廊上雕刻了孔子的形象，体现了法律与道德之间的联系。孔子作为中国历史上著名的思想家和教育家，他的教义强调道德修养和社会责任，这与法律的公正和道德基础相契合。尽管孔子的文化背景与美国法律体系不同，但他对道德与法治的重视，使得他的形象在最高法院的装饰中象征着对正义和伦理的尊崇，同时也反映了国际间文化的交流与融合。</response>
  <response id="p8-r4">美国最高法院的花岗岩雕刻中有孔子的雕像，反映了法治和伦理道德的理念。孔子是中国古代思想家，以其对法律、道德和社会秩序的深刻见解而著称。他的教导强调了道德责任和个人在社会中的角色，这与美国宪法所追求的公正与平等的价值观相契合。通过将孔子纳入雕刻，最高法院表示对全球法律思想的认可，以及对建立一个基于道德和法律原则的社会的承诺。</response>
  <response id="p8-r5">美国最高法院的檐顶雕刻了孔子的形象，反映了孔子在法律与道德教育中的重要性。孔子是中国古代伟大的思想家和教育家，他提倡的伦理道德和社会正义理念影响了世界各国的法律和治理思想。在塑造美国法律体系时，许多开国元勋受到包括孔子在内的许多古代哲学家影响，因此将孔子雕刻在最高法院的装饰中，象征着法律与正义的普遍价值观。</response>
  <response id="p8-r6">美国最高法院的檐口上雕刻有孔子的形象，主要是为了彰显法律与道德的联系。孔子作为中国古代伟大的思想家和教育家，其教导强调伦理、社会秩序和道德责任，这些理念与西方法律体系中的正义、公平和社会秩序相呼应。将孔子的形象纳入最高法院的雕刻中，体现了对全球哲学和道德传统的尊重，同时也表明法律不仅仅是规则的集合，更是维护社会正义和人类尊严的重要工具。</response>
  <response id="p8-r7">美国最高法院的檐饰上雕刻有孔子的形象，是因为孔子在法律和伦理思想方面的贡献被广泛认可。孔子的教义强调正义、道德和社会秩序，这些理念与法治精神密切相关。最高法院作为美国法律体系的重要组成部分，雕刻孔子的形象旨在体现对追求公平、正义和道德教育的重视，同时也反映了对全球法律思想传统的尊重。</response>
  <response id="p8-r8">最高法院的雕刻中有孔子的形象，反映了对古代智慧和伦理思想的尊重。孔子是中国历史上重要的思想家，以其对法律、道德和社会秩序的贡献而著称。他的思想强调仁、礼、义，而这些理念在世界范围内影响了法律和政治哲学的发展。把孔子雕刻在最高法院的额楣上，象征着对公平正义和道德法律基础的追求，体现了不同文化对法治与人权的共同重视。</response>
  <response id="p8-r9">在美国最高法院的雕像上雕刻了孔子的形象，主要是因为孔子在法治和道德哲学方面的重要性。他的教义强调仁、礼和正义，这些与美国法律和宪法的基本原则相契合。孔子的思想影响了许多国家的法律体系，并且他被视为道德和伦理的象征，因此在最高法院的雕刻中呈现出他的形象，以表明对公平正义理念的推崇。</response>
  <response id="p8-r10">美国最高法院的门廊装饰有孔子的雕刻，体现了对法律和道德哲学的崇敬。孔子作为中国古代伟大的思想家和教育家，以其强调伦理、正义和社会和谐而闻名，其思想对全球的法律和道德体系产生了深广影响。在最高法院的建筑装饰中，孔子被视为促进法律与道德结合的重要人物，凸显出人类追求公正和智慧的共同价值。</response>
  <response id="p8-r11">美国最高法院的檐楣上雕刻了孔子的形象，体现了这一机构对法律和道德哲学的重视。孔子作为中国古代伟大的思想家和教育家，他的思想强调仁、义和道德规范，这些理念在很多文化中都被视为法律和正义的基石。通过将孔子雕刻于此，最高法院旨在彰显普世价值观和道德法律的连接，强调法律不仅关乎规则和秩序，也关乎人类的伦理和社会责任。</response>
  <response id="p8-r12">美国最高法院的雕刻中有孔子的形象，反映了法律和道德的结合以及对古代智慧的尊重。孔子作为中国古代伟大的思想家和教育家，强调伦理道德、社会和谐和正义，这些价值观对许多国家的法律体系都产生了深远影响。通过在最高法院的外立面上雕刻孔子的形象，意在表明法律不仅仅是规则的制定，更是社会道德和公正理念的体现。</response>
  <response id="p8-r13">美国最高法院的雕刻中包含了孔子的形象，主要是因为孔子在法律和伦理方面的影响力。孔子提倡的道德原则与正义思想，强调了社会秩序、礼仪以及个人修养，这些理念与西方的法律思想并不冲突，反而形成了互补。最高法院的设计意在体现法律的普遍原则和智慧，孔子的存在象征着人类对道德和公正追求的共同努力，突显了法律的文化根基和全球视野。</response>
  <response id="p8-r14">美国最高法院的雕刻中有孔子的形象，体现了法律和道德的智慧以及不同文化的融合。孔子是中国古代的伟大哲学家和教育家，他提倡的伦理道德观念和社会秩序对法律思想产生了深远影响。这一雕刻不仅代表了东亚文化对西方法律思想的贡献，也反映了多元文化在美国法律体系中占有一席之地，强调法律与道德之间的密切关系。</response>
  <response id="p8-r15">在美国最高法院的飞檐雕刻上有孔子的雕像，这体现了西方法律体系与东方哲学的交融。孔子作为中国古代杰出的思想家和教育家，他的伦理和道德哲学强调社会和谐、正义与个人责任，与美国宪法所倡导的法治精神相契合。因此，孔子的雕像不仅代表了古代智慧的传承，也反映了多元文化在法律思想中的重要性。</response>
  <response id="p8-r16">美国最高法院的圣坛上雕刻有孔子的雕像，反映了孔子在法律和道德领域的重要地位及其对西方法律思想的影响。孔子是中国古代伟大的思想家和教育家，他的伦理思想强调正义、道德和社会秩序，与西方的法治观念相得益彰。通过这种表现，最高法院旨在强调法律的道德基础以及对人类智慧的尊重，表明法律不仅仅是规则的集合，更是体现正义和公正的重要工具。</response>
  <response id="p8-r17">美国最高法院的雕刻中有孔子的形象，体现了对古代哲学和法律思想的尊重。孔子作为中国古代伟大的思想家和教育家，他的伦理道德和社会秩序理念影响深远，与西方的法治思想有一定的共鸣。将孔子的形象刻在最高法院的墙面上，象征着对正义、道德和良好治理的重视，展示了法律与伦理的紧密联系，强调了全球范围内对智慧和正义理想的共同追求。</response>
  <response id="p8-r18">美国最高法院的檐饰上雕刻了孔子的形象，主要是因为孔子被视为道德与法律的象征，他的思想对法律与伦理有着深远的影响。孔子强调的仁义、礼仪和政府的道德责任与法律的公正性密切相关，这使得他的形象成为法治与道德治理的重要象征。此外，最高法院作为司法机构，强调法律与伦理的结合，孔子作为儒家思想的代表，体现了这一理念。因此，孔子的雕刻在最高法院的建筑装饰中具有重要的象征意义。</response>
  <response id="p8-r19">美国最高法院的浮雕上雕刻孔子的原因主要是因为孔子在历史上对法律、道德和伦理思维的重大贡献。他的思想强调了社会秩序、正义和个人责任，这些原则与美国法律体系的基础相契合。通过将孔子的形象纳入最高法院的装饰，体现了对古代哲学和法律智慧的尊重，同时也强调了法律与道德的紧密关联。孔子的存在象征着对公正与道德理想的追求，强调了法律在维护社会和谐与正义方面的重要角色。</response>
  <response id="p8-r20">美国最高法院的浮雕上刻有孔子的雕像，这反映了孔子的思想对法律和道德的深远影响。孔子提倡的伦理道德和正义原则在许多文化中都有重要地位，特别是在法律领域，以服务公共利益和维护社会秩序为核心。将孔子与其他历史伟人一同展现，象征着国际法律和道德观念的融合，强调法律不仅仅是规则的集合，还需要建立在深厚的道德基础之上。</response>
  <response id="p8-r21">美国最高法院的浮雕上有孔子的雕刻，是因为孔子在法治和道德教育方面的影响深远。他被视为伦理和社会秩序的倡导者，其思想强调正义、平等和个人的道德责任，这与美国法治的核心价值观相契合。通过展示孔子的形象，最高法院强调了全球法理的联系，表明法治不仅仅是西方的理念，而是人类共同的智慧与经验。</response>
  <response id="p8-r22">美国最高法院的华盖装饰上雕刻了孔子的形象，以彰显法律与道德的关系。孔子是中国历史上重要的哲学家和教育家，他的思想强调仁、义、礼等价值观，这些对治理社会和法律制度的发展有深远影响。将孔子的雕像置于最高法院的雕塑中，表现了对古代智慧的尊重，同时也反映了全球性思想对美国法律体系的影响，因此孔子的形象象征着正义与德行的价值。</response>
  <response id="p8-r23">美国最高法院的浮雕上刻有孔子的雕像，反映了法律和道德智慧的普遍价值。孔子作为古代中国著名的哲学家和教育家，强调仁、义、礼等伦理道德原则，这些理念与西方法律体系的基础相通。最高法院的设计旨在传达法律不仅仅是规则的集合，更是体现人类共同价值与智慧的领域，因此在建筑装饰中融入孔子的形象，象征着对道德法律思想的尊重与借鉴。</response>
  <response id="p8-r24">美国最高法院的雕刻中有孔子的形象，这反映了孔子在法律和道德教育方面的深远影响。作为中国古代伟大的哲学家和教育家，孔子强调伦理、正义和社会和谐，这些理念与法律的基础密切相关。通过将孔子的雕像置于最高法院的浮雕中，表明了对普世价值观的重视，尤其是在法治和道德的语境下，展示了对传统智慧的尊重，以及在法律判断中引入德治的重要性。</response>
  <response id="p8-r25">美国最高法院的檐饰上雕刻了孔子的形象，象征着法律与道德的结合。孔子是中国古代伟大的思想家和教育家，他的教义强调伦理、道德和社会责任，这些理念对法律体系的建立有重要影响。在美国政府的法治理念中，柔和的智慧与伦理道德的考量同样重要，因此在最高法院的装饰中加入孔子的雕刻，表明对这些传统思想的尊重和重视，体现了对正义与道德的追求。</response>
  <response id="p8-r26">美国最高法院的饰带上雕刻有孔子的形象，主要是因为孔子在中国文化中被视为伦理和道德的伟大思想家，其教育思想和政治理念影响深远。美国建国者重视法治和道德原则，而孔子的思想强调社会和谐、正义与诚实，符合美国法律体系的基础。通过在最高法院的建筑上加入孔子的雕像，旨在强调法律与道德之间的联系，以及不同文化在促进公正与和谐社会中的重要性。</response>
  <response id="p8-r27">美国最高法院的檐口上雕刻了孔子的形象，这体现了对法律和道德智慧的重视。孔子作为中国古代著名的思想家，强调伦理道德和理性治理，对世界各国的法律思想产生了深远的影响。美国作为一个多元文化的国家，尊重并吸收了不同文化的智慧，孔子的雕像象征着对道德和公正的追求，同时也体现了司法系统中法理和道德的结合。</response>
  <response id="p8-r28">美国最高法院的檐饰上雕刻孔子的形象，反映了儒家思想对法律和道德的重要影响。孔子被视为东方的伟大哲学家和道德家，他的教义强调伦理、正义和社会和谐，这与西方法律体系中对正义、秩序的追求相呼应。通过这一雕刻，最高法院表达了对跨文化智慧的尊重，强调不同文化在法治和道德建设中的共同价值。</response>
  <response id="p8-r29">在美国最高法院的檐口上雕刻了孔子的形象，体现了对法治和道德的重视。孔子是中国古代伟大的思想家和教育家，他的哲学强调伦理、正义和社会和谐，这些观念与西方法律体系中的正义原则相呼应。通过将孔子的雕像融入最高法院的装饰，彰显了跨文化的智慧交流和道德价值观的重要性，强调了法律不仅是一套规则，更是建立在道德基础上的。</response>
  <response id="p8-r30">美国最高法院的檐墙上雕刻孔子的原因在于他作为世界著名的哲学家和教育家的地位，代表了法治和道德伦理的重要性。孔子的思想强调了社会秩序、公共道德和人际关系的和谐，这与法律的基本原则相呼应。雕刻孔子是为了体现法院在实现公正与道德责任方面的价值，同时也展示了法律与哲学、文化之间的紧密联系。这种象征性雕刻提醒人们法律不仅仅是规则的集合，更是道德和伦理的延续。</response>
  <response id="p8-r31">美国最高法院的山墙上雕刻孔子的原因是为了强调法律和道德的关系，以及儒家思想对法治的影响。孔子是中国古代伟大的思想家和教育家，他的教义强调仁义、礼法和社会和谐，这与西方法律体系的原则有相通之处。将孔子的雕像纳入法院的装饰，反映出对全球法律传统的尊重和对道德原则在人类立法中的重要性的认可。通过这个雕刻，最高法院体现了追求公正和伦理的普遍理念。</response>
  <response id="p8-r32">美国最高法院的山墙上雕刻孔子的原因在于孔子是古代中国著名的思想家和教育家，他的思想强调法律、道德和正义，影响了许多文化的法律体系。作为中国儒家思想的创始人，孔子的理念与美国法律体系所重视的公平、道义和社会秩序相呼应。此外，最高法院的雕刻艺术旨在体现不同文化对法律和正义的贡献，孔子的雕像象征着全球范围内对法治和道德的尊重。</response>
  <response id="p8-r33">美国最高法院的雕刻中有孔子的形象，这反映了对法律和道德哲学的重视。孔子是中国古代著名的思想家，强调伦理、道德和社会秩序，他的思想对法律制度和社会治理产生了深远影响。将孔子雕刻在最高法院的浮雕上，象征着法律不仅仅是规则的集合，更是建立在道德和伦理基础上的治理，为国家的公正和和谐提供指导。这也体现了对不同文化和文明思想的尊重与吸纳。</response>
  <response id="p8-r34">美国最高法院的华表上刻有孔子的雕塑，主要是因为孔子是中国古代伟大的思想家和教育家，他的儒家思想对法律、道德和社会秩序有深远的影响。最高法院象征着法律和正义，与孔子的理念相契合，反映了对法治和伦理的重视。通过这种雕刻，最高法院表达了对历史上重要法律思想的尊重，并强调法律与道德之间的联系。</response>
  <response id="p8-r35">在美国最高法院的檐石上雕刻孔子的形象，反映了对法治和道德的重视。孔子作为中国历史上著名的思想家和教育家，其伦理思想和对社会秩序的重视与西方的法治理念相契合。美国的法律体系受到多种文化和哲学的影响，包括古希腊、罗马以及东方的哲学，孔子的雕像象征着对智慧与伦理的普遍尊重，强调了法律与道德之间的联系。通过将孔子的形象融入到法院的设计中，意在体现法律不仅仅是规则的集合，更是基于正义和道德原则的社会契约。</response>
  <response id="p8-r36">美国最高法院的壁梁上雕刻有孔子的形象，主要是因为孔子代表着法律、公正和道德教育的理念。他的思想对法治和道德规范有深远的影响，强调仁、义、礼的重要性，这与美国法律体系所倡导的基本原则相契合。通过将孔子雕刻在法院的壁梁上，反映了对世界各地智慧和传统的尊重，以及将这些价值观纳入美国法律教育和司法的愿望。</response>
  <response id="p8-r37">美国最高法院的飾帶上雕刻孔子的形象，反映了对人类法治和道德原则的尊重。孔子作为中国古代的哲学家，强调伦理道德和社会和谐，这与美国宪法所倡导的法治精神相契合。将孔子的雕像置于最高法院的飾帶上，象征着对普世法律原则和正义的追求，以及对历史上伟大思想家的致敬，表明法律的基础不仅源于西方思想，也受到东方哲学的影响。</response>
  <response id="p8-r38">美国最高法院的弗里兹上雕刻了孔子的形象，是因为孔子在古代中国对法律和道德治理有着深远的影响。他提倡的仁义道德和社会和谐的理念，与美国建立法治社会的价值观相吻合。最高法院的设计反映了对历史上伟大法治思想家的尊重，孔子作为儒家思想的代表，象征着智慧和正义，因此他的雕刻被纳入法院的艺术表现之中，以强调法律与道德的结合。</response>
  <response id="p8-r39">美国最高法院的华丽檐口上雕刻有孔子的形象，反映了法律与道德智慧之间的联系。作为儒家思想的创始人，孔子强调伦理道德、社会秩序与良好治理的价值，深刻影响了东亚文化和思想。他的理念与法律的公正和伦理原则相吻合，体现了法律不仅是规章制度，更是一种道德责任。此雕刻象征着法律的智慧和人类对公正与道德的追求。在美国建立法律体系时，借鉴了包括孔子在内的多位伟大思想家的理论，以构建一个更为公正的社会。</response>
  <response id="p8-r40">美国最高法院的壁柱上雕刻孔子的形象，体现了法律和道德的结合。孔子作为中国伟大的思想家和教育家，其思想强调伦理、正义和社会责任，这些理念与西方法律体系中的公正与道德原则相呼应。之所以选择孔子，是因为他的思想在全球范围内都具有深远的影响，并且在塑造西方法律与治理观念中发挥了重要作用，象征着跨文化的法律智慧与伦理传统。</response>
  <response id="p8-r41">在美国最高法院的檐廊上雕刻了孔子的形象，主要是因为孔子是儒家思想的创始人，他的伦理和法律理念对法治和政府治理产生了深远的影响。作为古代中国最重要的哲学家之一，孔子提倡的正义、道德与社会和谐与美国建国时强调的法治原则相呼应，显示出古代智慧对现代法律体系的影响。因此，将孔子的雕像刻在最高法院的檐廊上是对这种思想遗产的认可和致敬。</response>
  <response id="p8-r42">美国最高法院的檐饰上雕刻着孔子的形象，反映了法律与道德之间的联系。孔子作为中国古代著名的思想家和教育家，强调仁、义和礼的重要性，象征着道德品质和社会正义，这与美国法律系统追求公正和平等的理念相呼应。通过将孔子的形象融入最高法院的装饰，彰显了跨文化的法律思想和对道德法则的重视，强调了法律不仅仅是规则的集合，更是道德与公正的体现。</response>
  <response id="p8-r43">美国最高法院的华丽雕刻中包括孔子的形象，反映了法律与道德伦理的深厚联系。孔子作为中国古代伟大的思想家和教育家，以其伦理学和政治理念影响了东亚文化，强调仁义、礼法与社会和谐。将孔子雕刻在最高法院的壁饰上，体现了美国法律系统对普世价值和道德原则的重视，以及对人类智慧和治理思想的尊重，通过这种方式强调法治与道德的内在联系。</response>
  <response id="p8-r44">美国最高法院的华盖上雕刻有孔子的形象，反映了孔子作为中国古代伟大思想家的重要性，特别是在法律和道德教育方面的贡献。孔子的教义强调伦理道德、社会秩序和正义，影响了许多文化的法律体系。他的存在象征着全球性的法律哲学和道德法律观，表明美国在司法和法律理念上也承认并尊重其他文化的智慧和价值观。</response>
  <response id="p8-r45">美国最高法院的浮雕上有孔子的雕刻，反映了孔子作为道德与法律思想的重要象征。孔子强调伦理、社会秩序和政府的正义性，他的教义影响了诸多文化和法律体系，尤其是在强调仁义和社会责任的方面。将孔子的形象刻在最高法院的浮雕中，体现了对智慧、正义与伦理基础的追求，同时也表明美国法律体系在历史上受到多元文化思想的影响。</response>
  <response id="p8-r46">美国最高法院的雕刻上有孔子的形象，反映了对法律和正义的重视。孔子是中国古代伟大的哲学家和思想家，他的伦理道德思想强调仁、义和礼，这些原则在法律和治理中具有重要意义。通过将孔子与其他历史和文化中的重要人物一起刻画，最高法院表明了法律是一个全球性和多元文化的概念，体现了对智慧和道德法则的跨文化尊重。</response>
  <response id="p8-r47">美国最高法院的檐墙上雕刻有孔子的形象，主要是因为孔子作为古代中国的伟大哲学家和教育家，其思想强调道德、正义和社会秩序，这与美国法治的原则相契合。孔子的教育理念和伦理思想对法律和治理有着深远的影响，因此在最高法院的装饰中包含孔子的雕像，体现了对普世价值和法律精神的认同与尊重，同时也强调了法律与道德之间的联系。</response>
  <response id="p8-r48">美国最高法院的檐饰上雕刻了孔子的形象，主要是因为孔子在古代中国的思想对法律和道德有深远的影响。他强调的伦理道德、社会秩序和个人责任与西方法治理念有着类似的价值观，因此孔子的形象被视为象征智慧和公正的一个重要代表。此外，这一雕刻也体现了对古代经典哲学的尊重，表达了对人类社会治理和法律制度发展中的历史智慧的认可。</response>
  <response id="p8-r49">美国最高法院的檐座上雕刻孔子的形象，反映了法律和道德的普遍价值观。孔子作为中国古代伟大的哲学家和教育家，其思想强调仁、义和礼，这些原则在许多文化中都被视为促进社会和谐与正义的基础。加入孔子的雕像，突显了法律体系对人性和道德责任的重视，同时也体现了东西方文化在法律和政治思想上的相互影响。</response>
  <response id="p8-r50">在美国最高法院的雕饰中有孔子的雕刻是因为孔子在中国历史上是著名的思想家和教育家，其伦理思想和对法治的重视对世界各国的法律和道德体系产生了深远的影响。孔子的教义强调诚信、礼仪和社会责任，这些价值观与美国的法律传统和民主理念相契合。通过将孔子的形象雕刻在最高法院的壁面上，体现了美国对不同文化和思想来源的尊重，同时也强调了法治与道德相结合的重要性。</response>
  <response id="p8-r51">美国最高法院的檐壁上雕刻孔子的原因在于他在法治和伦理思考方面的重大影响。孔子强调仁、义和道德领导的重要性，这与美国法律体系中的某些原则相吻合。作为古代中国最重要的哲学家之一，孔子的思想不仅影响了中国的文化和法律，也体现了普世的道德价值。在最高法院的雕刻中展示孔子的形象，彰显了对古代智慧和正义原则的尊重，强调了法律与道德之间的联系。</response>
  <response id="p8-r52">在美国最高法院的浮雕上雕刻孔子的原因是为了体现法律和道德的哲学传统，孔子作为儒家思想的创始人，强调伦理、道德和社会和谐，对法律和治理有深远的影响。他的思想在历史上对许多文化，特别是东亚国家的法律体系产生了重要影响。通过在最高法院的装饰中加入孔子的雕刻，彰显了美国法律体系对人类智慧和伦理道德传统的尊重，以及其对公平、正义的追求。</response>
  <response id="p8-r53">美国最高法院的檐柱上雕刻了孔子的形象，象征着法律与道德的结合。孔子作为中国古代的伟大哲学家和教育家，他的思想强调社会秩序、道德伦理和仁爱精神，这些思想对西方的法律观念也产生了影响。通过将孔子的形象纳入司法建筑的一部分，强调了法治的普遍价值观和人类共同的道德追求。</response>
  <response id="p8-r54">美国最高法院的檐梁上雕刻有孔子的形象，反映了对古代哲学家和法治思想家的尊重。作为儒家学派的创始人，孔子强调道德、正义和社会和谐，而这些理念与美国法治的基础相契合。雕刻孔子的形象不仅展示了世界文化的多样性，也突显了法治在不同文化传统中的共同价值。这种文化象征性为最高法院增添了全球视野，同时强调了道德和伦理在法律体系中的重要性。</response>
  <response id="p8-r55">美国最高法院的檐廊雕刻了孔子的形象，体现了对法律与伦理的重视。孔子作为中国古代伟大的思想家和教育家，他的伦理思想特别强调社会和谐、正义与道德，这与法治的核心理念有着深刻的共鸣。雕刻孔子不仅代表了西方法律体系的多元文化源流，也寓意着法律不仅仅是制裁和规章，更是公正与道德的体现。通过这种方式，最高法院向人们传达了维护社会正义和道德责任的重要性。</response>
  <response id="p8-r56">美国最高法院的饰条上雕刻了孔子的形象，主要是因为孔子作为古代中国的伟大哲学家和教育家，对法律、道德和社会秩序有着深远的影响。他的思想强调伦理、正义和礼仪，这些理念与美国法律体系中的公平与正义的原则相契合。通过在最高法院的装饰中加入孔子的形象，体现出对全球智慧和人类文明的尊重，同时强调法律与道德之间的关联。</response>
  <response id="p8-r57">美国最高法院的浮雕上雕刻了孔子的形象，主要是因为孔子作为古代中国伟大的思想家和教育家，代表了法律与道德的结合。他的教义强调社会和谐、正义与个人的责任，这与美国法律体系的核心价值观相契合。通过展示孔子的形象，最高法院旨在强调法律不仅是制度和规则，更是基于普遍道德和伦理的原则。孔子的理念影响了全球的法律思想，因此在这一重要的法律建筑上雕刻他的形象，彰显了对普世价值的尊重和对法律的崇高理想。</response>
  <response id="p8-r58">美国最高法院的檐口雕刻了孔子的形象，反映了孔子对法律和伦理思想的深远影响。孔子作为古代中国著名的思想家，他的儒家思想强调社会和谐、道德责任和法治，这些理念与美国法律体系的基础相呼应。雕刻孔子旨在表彰他在促进正义和道德治理方面的重要性，同时也体现了全球文化对美国法律思想的贡献。</response>
  <response id="p8-r59">在美国最高法院的饰带上雕刻孔子的原因在于孔子作为中国古代伟大的哲学家和教育家，对道德、法律和政治哲学有深远的影响。他提倡的仁爱和正义原则，与美国的法律体系中强调的道德价值观相呼应。此外，孔子在促进社会秩序和良好治理方面的思想，与美国宪法所追求的正义和公共利益相一致，因此在最高法院的雕刻中体现了他对人类法治和伦理的重要贡献。</response>
  <response id="p8-r60">美国最高法院的雕刻中有孔子的形象，反映了孔子作为古代哲学家和教育家的重要性，他的思想强调道德、正义和法治。这一雕刻体现了对古代智慧的尊重，以及对法律和社会治理中道德原则的认可。孔子的理念与美国法律体系中推崇的伦理和责任观念相契合，因此在最高法院的装饰中展现他的形象，象征着人类文明的共同价值观。</response>
  <response id="p8-r61">美国最高法院的浮雕上刻有孔子的雕像，是因为孔子是古代中国著名的哲学家和教育家，他的思想对法律、道德和社会秩序有深远的影响。孔子提倡的仁、义、礼等价值观与法律的基本原则相契合，体现了对人伦关系和社会和谐的重视。通过在最高法院的装饰中包含孔子的雕像，意在强调法律和正义的普遍性以及从不同文化中汲取智慧的重要性。</response>
  <response id="p8-r62">美国最高法院的檐墙上雕刻孔子的形象，体现了中国古代哲学对法律和伦理思想的影响。孔子作为儒家学派的创始人，强调道德、正义和社会秩序，这些理念与美国宪法中追求公正与平等的价值观不谋而合。通过将孔子的形象纳入最高法院的装饰，表明了对其智慧的尊重，并暗示法律不是单纯的规则，而是应根植于更深的道德和伦理标准之中。</response>
  <response id="p8-r63">美国最高法院的横梁上雕刻有孔子的形象，反映了孔子在法律和道德教育中的重要性。孔子作为中国古代伟大的思想家和教育家，他的哲学和伦理观念强调了正义、道德和社会责任，这与美国法律体系追求的公正与平等的理念相契合。此外，孔子的思想影响了东亚文化圈，并且在全球范围内对法治与道德教育产生了深远的影响，体现了多元文化对美国法律传统的尊重与包容。</response>
  <response id="p8-r64">美国最高法院的檐托上雕刻有孔子的形象，反映了法治和道德伦理的重要性。孔子作为中国古代伟大的哲学家和教育家，以其崇高的道德标准和对社会秩序的重视而闻名，他的思想影响了许多国家的法律和政治理论。在美国，最高法院的设计旨在体现多元文化的法律传统，孔子的雕像象征着对正义、道德和法治原则的尊重，强调了文明社会中法律与伦理的相辅相成。</response>
  <response id="p8-r65">美国最高法院的雕刻中有孔子的雕像，是因为他被视为法律和道德哲学的先驱。孔子的思想强调伦理、社会和谐以及以德治国，这些理念与法律的公正和伦理基础相吻合。通过在最高法院的装饰中加入孔子的形象，体现了对法律理想和道德价值观的重视，同时也反映了东西方文化在法律与伦理思想上的相互影响。</response>
  <response id="p8-r66">美国最高法院的山花雕刻中有孔子的雕像，反映了对法治和道德智慧的尊重。孔子是中国古代伟大的思想家和教育家，他的哲学强调道德、伦理和合理的治理，这些理念与西方法治思想有共通之处。通过将孔子雕刻在最高法院的建筑上，表明了美国法律体系继承和尊重全人类的智慧与文明，强调了法律不仅仅是规则的集合，更是道德和社会正义的体现。</response>
  <response id="p8-r67">美国最高法院的雕刻中有孔子的形象，反映了法律和道德思想的深厚根基。孔子作为中国古代伟大的思想家和教育家，强调伦理、道德和社会秩序的重要性，这与西方法律体系中对正义和伦理的追求有着相似之处。将孔子的雕刻置于最高法院的壁饰上，象征着对智慧和道德原则的尊重，强调了国际间对法治和人权的共同价值观念。这样的设计也体现了多元文化对美国法律和社会发展的影响。</response>
  <response id="p8-r68">美国最高法院的檐饰上雕刻孔子的原因在于孔子作为古代中国的著名哲学家和教育家，其思想强调道德、法律和社会秩序的重要性，这与美国法律体系中关于正义和伦理的核心价值相符。雕刻孔子的形象体现了法律与哲学的结合，强调了世界各地对法律与道德理念的共同尊重，也展示了美国对于全球文化的开放与包容。</response>
  <response id="p8-r69">美国最高法院的檐饰上雕刻了孔子的形象，反映了法治和道德伦理的重要性。孔子是中国古代伟大的思想家和教育家，他的思想强调仁、义、礼、智等道德原则，与西方法治理念相辅相成。在这个法庭的雕塑中，孔子代表着智慧和道德的追求，象征着对法律公正和社会正义的崇高理想，因此被纳入到体现法律与道德的文化象征中。</response>
  <response id="p8-r70">美国最高法院的浮雕中有孔子的雕像，主要是因为孔子在伦理和法律方面的影响。孔子作为中国古代伟大的思想家和教育家，他的教义强调道德、正义和社会秩序，这与法治的理念相契合。最高法院的建筑设计旨在体现全球范围内的法律传统和哲学思想，孔子作为儒家思想的象征，代表了普遍的法律和道德原则，因此被纳入到这一重要的法律机构的装饰中。</response>
  <response id="p8-r71">在美国最高法院的雕刻浮雕中有孔子的形象，反映了他在法律与道德哲学方面的影响。孔子是中国古代伟大的思想家与教育家，他的教导强调伦理、正义和社会和谐，这些理念对法律体系及其公正原则的发展有着重要的启示。美国的法律体系受到多种文化和哲学传统的影响，孔子的存在象征着对道德伦理的重视，强调了法治与道德之间的联系。</response>
  <response id="p8-r72">在美国最高法院的浮雕上雕刻孔子的原因与孔子在法治和道德哲学方面的重要性有关。孔子作为中国伟大的思想家，以其倡导的仁、义、礼、智等伦理原则影响了东亚文化，并且促进了社会的和谐与稳定。他的思想强调治国理政的智慧，使得法律不仅仅是制度，而是一种道德责任。因此，最高法院通过雕刻孔子，体现了对法律和伦理原则的重视，强调了法律与道德的密切联系。</response>
  <response id="p8-r73">美国最高法院的饰带上刻有孔子的雕像，反映了该院在法律和道德哲学方面受到的广泛影响。孔子是中国古代著名的哲学家和教育家，他的思想强调伦理、正义和社会秩序，与美国法律体系倡导的公正和道德原则相呼应。这一雕刻象征着对历史上伟大思想家的尊重，表明法律不仅仅是制定规则的过程，还要与道德和伦理相结合，以促进社会的和谐与正义。</response>
  <response id="p8-r74">美国最高法院的横梁上雕刻孔子的形象，反映了西方法律与东方思想的融合。孔子是中国古代伟大的思想家与教育家，他的伦理和政治哲学强调道德、正义与社会和谐，这些理念与美国宪法所倡导的法律原则有相通之处。通过雕刻孔子的形象，最高法院强调了法律的普世价值和人类理智的智慧，同时也展示了对不同文化在法治和道德建设方面贡献的尊重。</response>
  <response id="p8-r75">美国最高法院的匾额上雕刻了孔子的形象，因为孔子的思想在法律和道德教育方面有着深远的影响。他被视为儒家文化的代表，强调仁、义、礼的重要性。这些理念在塑造西方法律思想和司法体系中发挥了重要作用，体现了对道德与正义的追求，反映了最高法院作为维护宪法和法律公正的机构，承认并融合不同文化传统中的智慧。</response>
  <response id="p8-r76">美国最高法院的檐廊上雕刻有孔子的形象，主要是因为孔子在中国文化中被视为道德的典范和智慧的象征，他的教导强调正义、伦理和社会和谐，这与法治的原则相契合。雕刻孔子体现了对普世价值的尊重，同时反映了美国法律体系受到了各种文化和哲学思想的影响，尤其是强调道德和法律之间关系的思想。通过这一雕刻，最高法院传达了对古代智慧和法律精神的承认与敬重。</response>
  <response id="p8-r77">美国最高法院的檐饰上雕刻了孔子的形象，反映了法律与道德之间的深刻联系。孔子是中国古代伟大的思想家和教育家，他的教义强调仁、义和社会和谐，这些理念与西方法治原则相呼应。最高法院通过这一雕刻，象征性地表达了对道德法律传统的重视，体现了多元文化的包容性，以及对智慧和法律公正的追求。</response>
  <response id="p8-r78">美国最高法院的檐饰上雕刻了孔子的形象，反映了对法律和道德的重视。孔子是中国古代伟大的哲学家和教育家，他的思想强调仁、义和礼，对社会秩序和道德伦理有深远影响。最高法院将他的雕塑纳入其装饰中，象征着法律的普遍价值观以及对智慧与正义的追求，体现了法律在不同文化和历史背景下的共同基础。</response>
  <response id="p8-r79">美国最高法院的檐口雕刻有孔子的雕像，反映了孔子在法治和伦理道德方面的重要性。孔子的思想强调道德教育、社会和谐和良善治理，这些理念与美国法律体系和司法公正的核心价值观相契合。因为最高法院不仅是法律机构，也是体现社会公义和道德标准的地方，孔子的雕像象征着对智慧和法律公平的追求，展示了其对世界各国法治思想的影响。</response>
  <response id="p8-r80">美国最高法院的雕刻中有孔子的形象，主要是因为孔子代表了古代智慧和道德伦理，他的思想对法治和社会秩序有深远的影响。孔子的教导强调仁义和和谐，这与法律系统的基础价值观相契合。雕刻孔子的形象，体现了美国法律思想中对古代哲学的尊重，并且象征着对道德与公正的追求。</response>
  <response id="p8-r81">美国最高法院的檐板上雕刻有孔子的形象，反映了美国法律和司法体系中对古代思想的尊重。孔子作为中国古代伟大的思想家和教育家，他的伦理和政治思想强调道德、正义和良治，这些理念与西方的法治精神有相通之处。在美国建国初期，许多法律学者和政治家受到儒家思想的影响，认为这些思想能为社会提供道德指南，促进公民的责任感与社会和谐。因此，孔子的雕刻象征着对道德法治和人文精神的承认。</response>
  <response id="p8-r82">美国最高法院的墙饰雕刻有孔子的画像，反映了孔子在法律与道德哲学中的重要地位。他的思想强调正义、伦理和社会和谐，这与法律的基本原则相呼应。孔子的儒家思想对西方法治观念产生了一定影响，特别是在强调个人的责任和道德义务方面。因此，这一雕刻象征着对法律、正义以及普世价值的尊重，体现了多元文化在法律体系中的融合。</response>
  <response id="p8-r83">美国最高法院的檐口雕刻了孔子的形象，反映了孔子作为伟大的思想家和教育家的影响力，以及他对法律和道德的重视。孔子强调的仁、义、礼的原则与美国法律体系中的正义、公平和道德基石相呼应。这一雕刻意在表明，法律不仅是规则和程序，更是建立在伦理和人文传统之上的，因此孔子的雕像象征着对法治和正义理念的尊重与认可。</response>
  <response id="p8-r84">美国最高法院的檐饰上雕刻了孔子的形象，反映了对法律和道德教育的重视。孔子是中国著名的哲学家和教育家，他的思想强调伦理、正义和社会秩序，这与法律的基本原则相契合。美国的法治理念受到西方哲学的影响，但孔子关于道德和责任的教导也为法律的精神提供了重要的文化参考。因此，这样的雕刻不仅是对历史和文化的认同，也是对法律精神的弘扬。</response>
  <response id="p8-r85">美国最高法院的门廊上有孔子的雕刻，反映了西方法律思想与东方哲学的结合。孔子作为中华文化的伟大思想家和教育家，倡导的伦理道德、正义和社会和谐的理念影响深远，对法律、道德和治理的理解具有普遍意义。他的雕刻象征着对智慧的重视和对法治原则的尊重，强调了法律不仅仅是条文，更是伦理和道德的体现。这种包容不同文化的思想也反映了美国法律体系的多元性。</response>
  <response id="p8-r86">美国最高法院的檐座上雕刻有孔子的形象，反映了孔子作为道德和法律哲学的重要性。他的教导强调伦理、正义和社会责任，这与美国法律体系中对公正和道德的追求相契合。此外，孔子被视为思想家和教育家的代表，他的理念影响了东亚甚至全球的法治思想。因此，孔子的雕塑不仅象征着文化多样性，也彰显了法律与道德之间的紧密联系。</response>
  <response id="p8-r87">美国最高法院的镌刻中有孔子的雕像，这是因为孔子被视为法律和道德的奠基人之一，体现了法律与伦理的结合。他的教义强调正义、诚实和社会责任，这些理念与美国法律体系的基础相辅相成。此外，雕刻孔子象征着来自不同文化的智慧对司法和法律思想的贡献，体现了多元文化的融合和尊重。</response>
  <response id="p8-r88">美国最高法院的山花上雕刻了孔子的形象，是为了体现法律与道德之间的关系。孔子作为儒家思想的创始人，强调了伦理、正义和社会和谐的重要性，他的思想在法律的制定和实施中起到了深远的影响。通过将孔子的雕像纳入最高法院的装饰，意在强调法律不仅是规则的体系，还应当蕴含道德原则，推动社会的公平与正义。这一设计体现了法律与伦理的结合，反映了美国法律传统中包含的深厚哲学背景。</response>
  <response id="p8-r89">美国最高法院的饰带上雕刻孔子的形象，反映了孔子对法治和伦理道德的重视，以及他的思想对西方法律与政治哲学的影响。孔子提倡的“仁义”和社会和谐的理念与美国法治精神相契合，体现了对全球文化和思想传统的尊重。这一雕刻不仅代表了对孔子作为思想家的认可，也象征着法律与道德之间的紧密联系和对正义的追求。</response>
  <response id="p8-r90">美国最高法院的檐柱上雕刻了孔子的形象，体现了孔子对法律、道德和社会秩序的深刻影响。孔子作为中国古代伟大的思想家和教育家，其思想强调伦理道德、正义和社会责任，这些理念与西方法律体系的基石相似。因此，在最高法院的装饰中引用孔子的雕像，象征着对正义和道德法则的尊重，彰显出法律不仅是规则的集合，更是道德与智慧的体现。</response>
  <response id="p8-r91">美国最高法院的檐部雕刻有孔子的形象，反映了儒家思想在西方法律和道德观念中的影响。孔子作为古代中国伟大的哲学家和教育家，他的教义强调道德、正义和社会秩序，这与美国法律体系中的核心价值观相契合。通过将孔子的雕像纳入建筑设计，表明了对古典智慧和伦理原则的认可，以及它们在建立和维护法律制度中的重要性。这样的设计不仅象征着对全球法律文化的尊重，也提醒人们法律与道德的紧密关系。</response>
  <response id="p8-r92">美国最高法院的壁饰上雕刻有孔子的形象，反映了法律与道德的深厚联系。孔子是中国古代著名的哲学家和教育家，他的思想强调伦理道德、社会和谐及正义，这与法治的核心理念相吻合。美国建国时期，许多法律思想受到儒家文化的影响，孔子作为一个道德象征，被认为能够代表一种理想的治国哲学。因此，孔子的雕刻出现在最高法院的壁饰上，体现了对法治和道德伦理的重视。</response>
  <response id="p8-r93">美国最高法院的墙饰上雕刻有孔子的形象，反映了法律与道德哲学的深刻联系。孔子是中国古代著名的哲学家和教育家，他倡导的仁义礼智等伦理道德理念对于人类社会的法律制度产生了深远影响。将孔子的雕像置于最高法院的墙上，象征着对公正、道德和伦理原则的重视，同时也体现了法律的普遍性和跨文化的智慧。</response>
  <response id="p8-r94">美国最高法院的檐壁上刻有孔子的雕像，反映了中国哲学对法治和伦理的重要贡献。孔子强调道德、正义和社会和谐的原则，这与美国法律体系追求的公正和道德标准相吻合。将孔子的形象置于如此重要的建筑上，象征着全球思想对民主、法律和公共道德的影响，展现了法律传统的多元性和国际性。</response>
  <response id="p8-r95">美国最高法院的檐板上雕刻孔子的形象，反映了法治和道德伦理在法律体系中的重要性。孔子作为古代中国著名的思想家和教育家，其提倡的仁、义、礼等理念对人类社会的法律与道德观产生了深远影响。美国的法律体系受到了古代法律、哲学与道德思想的启发，孔子的雕刻象征着对人类智慧与法律原则的尊重，强调了法律不仅是规则的集合，更是道德与正义的体现。</response>
  <response id="p8-r96">美国最高法院的浮雕上雕刻有孔子的形象，反映了孔子对于法治和道德倡导的重要性。孔子是中国古代伟大的哲学家和教育家，他的思想强调伦理道德、社会正义和人的行为规范，这些理念与法治的基础相契合。 Supreme Court 希望通过这样的雕刻，体现出法律与道德的紧密联系，并彰显对人类智慧和伦理传统的尊重。</response>
  <response id="p8-r97">美国最高法院的浮雕上刻有孔子的雕像，这反映了孔子在法治、道德和伦理方面的重大影响。孔子被视为儒家思想的创始人，他强调的社会秩序、道德责任和诚实守信的价值观与美国法律体系中对正义和道德的追求相契合。通过展示孔子的形象，最高法院表明了对古代智慧和人类法治传统的尊重，同时强调法治的 universality 和文化多样性。</response>
  <response id="p8-r98">美国最高法院的霓虹灯上雕刻有孔子的形象，反映了法律与道德的结合。孔子是古代中国伟大的哲学家和伦理学家，他提倡的道德原则和正义理念深深影响了世界各地的法律思想。将孔子的雕像置于最高法院的装饰中，象征着对公正、智慧与道德的追求，并强调法律不仅仅是规则的集合，也需要伦理和正义的指导。</response>
  <response id="p8-r99">美国最高法院的檐墙雕刻了孔子的形象，反映了中国古代儒家思想对法律和道德的影响。孔子被视为道德和伦理的典范，他的教义强调仁爱、正义和社会责任，这与美国法治和公正的理念相符。通过在最高法院的装饰中展示孔子，强调了法律体系中对于道德原则的重要性，同时也体现了东西方文化交流的深远影响。</response>
  <response id="p8-r100">美国最高法院的海军雕刻包含了孔子的雕像，这反映了孔子对法律和道德教育的深远影响。孔子是中国古代的伟大思想家和哲学家，他的思想强调伦理、正义和社会和谐，对于法律体系和治理理念有着重要启示。将孔子的雕像置于最高法院的装饰中，体现了对传统道德法则的尊重，以及他在塑造正义和社会秩序方面的贡献，突显了法律与伦理的紧密关系。</response>
</responses>
