[
    {
        "response_id": "p7-r1",
        "pos_counts": {
            "ADP": 5,
            "PROPN": 1,
            "PUNCT": 15,
            "NOUN": 34,
            "ADV": 10,
            "VERB": 13,
            "DET": 2,
            "CCONJ": 3,
            "ADJ": 5,
            "NON-ZH": 1,
            "PART": 9,
            "NUM": 1
        },
        "tag_counts": {
            "P": 5,
            "NR": 1,
            "PU": 15,
            "NN": 34,
            "AD": 10,
            "VV": 9,
            "DT": 2,
            "VC": 1,
            "CC": 3,
            "JJ": 5,
            "NON-ZH": 1,
            "DEG": 3,
            "AS": 3,
            "VA": 3,
            "DEC": 1,
            "CD": 1,
            "LC": 2
        }
    },
    {
        "response_id": "p7-r2",
        "pos_counts": {
            "ADP": 5,
            "PROPN": 1,
            "PUNCT": 16,
            "NOUN": 41,
            "PART": 11,
            "ADV": 15,
            "VERB": 16,
            "ADJ": 5,
            "CCONJ": 6,
            "NON-ZH": 1,
            "DET": 3,
            "NUM": 1
        },
        "tag_counts": {
            "P": 5,
            "NR": 1,
            "PU": 16,
            "NN": 41,
            "DEG": 7,
            "AD": 15,
            "VA": 4,
            "JJ": 5,
            "VC": 1,
            "CC": 6,
            "NON-ZH": 1,
            "VV": 11,
            "AS": 2,
            "DT": 3,
            "LC": 1,
            "CD": 1,
            "DEC": 1
        }
    },
    {
        "response_id": "p7-r3",
        "pos_counts": {
            "ADP": 2,
            "PROPN": 2,
            "PUNCT": 12,
            "NOUN": 27,
            "ADV": 12,
            "VERB": 16,
            "PART": 9,
            "CCONJ": 4,
            "ADJ": 5,
            "NON-ZH": 1,
            "PRON": 1,
            "DET": 1
        },
        "tag_counts": {
            "P": 2,
            "NR": 2,
            "PU": 12,
            "NN": 27,
            "AD": 12,
            "VV": 12,
            "DEC": 2,
            "VC": 1,
            "CC": 4,
            "JJ": 5,
            "DEG": 4,
            "NON-ZH": 1,
            "PN": 1,
            "AS": 2,
            "VA": 3,
            "DT": 1,
            "ETC": 1
        }
    },
    {
        "response_id": "p7-r4",
        "pos_counts": {
            "ADP": 4,
            "PROPN": 1,
            "PUNCT": 10,
            "NOUN": 28,
            "ADV": 8,
            "VERB": 15,
            "PART": 7,
            "CCONJ": 6,
            "ADJ": 6,
            "NON-ZH": 1,
            "DET": 2,
            "PRON": 1,
            "NUM": 1
        },
        "tag_counts": {
            "P": 4,
            "NR": 1,
            "PU": 10,
            "NN": 28,
            "AD": 8,
            "VV": 13,
            "DEC": 2,
            "VC": 1,
            "CC": 6,
            "JJ": 6,
            "DEG": 3,
            "NON-ZH": 1,
            "DT": 2,
            "AS": 2,
            "VA": 1,
            "PN": 1,
            "CD": 1
        }
    },
    {
        "response_id": "p7-r5",
        "pos_counts": {
            "ADP": 3,
            "PROPN": 1,
            "PUNCT": 13,
            "NOUN": 31,
            "ADV": 12,
            "CCONJ": 5,
            "ADJ": 3,
            "NON-ZH": 1,
            "VERB": 16,
            "DET": 1,
            "PART": 5,
            "PRON": 1
        },
        "tag_counts": {
            "P": 3,
            "NR": 1,
            "PU": 13,
            "NN": 31,
            "AD": 12,
            "CC": 5,
            "JJ": 3,
            "NON-ZH": 1,
            "VV": 11,
            "VC": 1,
            "DT": 1,
            "AS": 1,
            "VA": 4,
            "DEG": 2,
            "ETC": 1,
            "DEV": 1,
            "PN": 1
        }
    },
    {
        "response_id": "p7-r6",
        "pos_counts": {
            "ADP": 3,
            "PROPN": 1,
            "PUNCT": 11,
            "NOUN": 24,
            "ADV": 14,
            "VERB": 16,
            "PART": 7,
            "CCONJ": 4,
            "ADJ": 2,
            "NON-ZH": 1,
            "DET": 2,
            "NUM": 1
        },
        "tag_counts": {
            "P": 3,
            "NR": 1,
            "PU": 11,
            "NN": 24,
            "AD": 14,
            "VA": 4,
            "DEC": 3,
            "VC": 1,
            "CC": 4,
            "JJ": 2,
            "DEG": 2,
            "NON-ZH": 1,
            "DT": 2,
            "VV": 11,
            "AS": 1,
            "CD": 1,
            "LC": 1
        }
    },
    {
        "response_id": "p7-r7",
        "pos_counts": {
            "ADP": 3,
            "PROPN": 1,
            "PUNCT": 10,
            "NOUN": 29,
            "PART": 6,
            "ADV": 10,
            "VERB": 11,
            "CCONJ": 5,
            "ADJ": 4,
            "NON-ZH": 1,
            "DET": 2,
            "X": 1,
            "NUM": 1,
            "PRON": 1
        },
        "tag_counts": {
            "P": 3,
            "NR": 1,
            "PU": 10,
            "NN": 29,
            "DEG": 4,
            "AD": 10,
            "VA": 1,
            "VC": 1,
            "CC": 5,
            "JJ": 4,
            "NON-ZH": 1,
            "DT": 2,
            "VV": 9,
            "AS": 1,
            "SB": 1,
            "DEC": 1,
            "CD": 1,
            "PN": 1
        }
    },
    {
        "response_id": "p7-r8",
        "pos_counts": {
            "ADP": 4,
            "PROPN": 2,
            "PUNCT": 10,
            "NOUN": 32,
            "ADV": 11,
            "VERB": 14,
            "PART": 8,
            "CCONJ": 4,
            "NON-ZH": 1,
            "DET": 3,
            "PRON": 1,
            "ADJ": 2
        },
        "tag_counts": {
            "P": 4,
            "NR": 2,
            "PU": 10,
            "NN": 32,
            "AD": 11,
            "VV": 9,
            "DEC": 1,
            "VC": 2,
            "DEG": 5,
            "CC": 4,
            "NON-ZH": 1,
            "DT": 3,
            "AS": 1,
            "VA": 3,
            "PN": 1,
            "DEV": 1,
            "JJ": 2
        }
    },
    {
        "response_id": "p7-r9",
        "pos_counts": {
            "ADP": 5,
            "PROPN": 3,
            "PUNCT": 14,
            "NOUN": 33,
            "ADV": 14,
            "VERB": 15,
            "PART": 10,
            "ADJ": 3,
            "CCONJ": 4,
            "NON-ZH": 1,
            "DET": 1,
            "NUM": 1,
            "SCONJ": 1,
            "PRON": 1,
            "X": 1
        },
        "tag_counts": {
            "P": 5,
            "NR": 3,
            "PU": 14,
            "NN": 33,
            "AD": 14,
            "VV": 9,
            "DEC": 3,
            "VC": 1,
            "JJ": 3,
            "DEG": 3,
            "CC": 4,
            "NON-ZH": 1,
            "DT": 1,
            "AS": 1,
            "VA": 5,
            "CD": 1,
            "MSP": 2,
            "CS": 1,
            "LC": 1,
            "PN": 1,
            "LB": 1
        }
    },
    {
        "response_id": "p7-r10",
        "pos_counts": {
            "ADP": 5,
            "PROPN": 2,
            "PUNCT": 11,
            "NOUN": 29,
            "PART": 7,
            "ADV": 12,
            "VERB": 10,
            "CCONJ": 5,
            "ADJ": 3,
            "NON-ZH": 1,
            "DET": 1,
            "X": 1,
            "PRON": 1
        },
        "tag_counts": {
            "P": 5,
            "NR": 2,
            "PU": 11,
            "NN": 29,
            "DEG": 5,
            "AD": 12,
            "VA": 2,
            "VC": 1,
            "CC": 5,
            "JJ": 3,
            "NON-ZH": 1,
            "DT": 1,
            "VV": 7,
            "AS": 1,
            "LC": 1,
            "LB": 1,
            "PN": 1
        }
    },
    {
        "response_id": "p7-r11",
        "pos_counts": {
            "ADP": 3,
            "PROPN": 2,
            "PUNCT": 10,
            "NOUN": 28,
            "ADV": 12,
            "VERB": 14,
            "CCONJ": 6,
            "ADJ": 5,
            "PART": 7,
            "NON-ZH": 1,
            "DET": 2
        },
        "tag_counts": {
            "P": 3,
            "NR": 2,
            "PU": 10,
            "NN": 28,
            "AD": 12,
            "VV": 10,
            "VC": 1,
            "CC": 6,
            "JJ": 5,
            "DEG": 5,
            "NON-ZH": 1,
            "DT": 2,
            "AS": 1,
            "VA": 3,
            "LC": 1
        }
    },
    {
        "response_id": "p7-r12",
        "pos_counts": {
            "ADP": 5,
            "PROPN": 1,
            "PUNCT": 11,
            "NOUN": 31,
            "ADV": 12,
            "VERB": 15,
            "PART": 8,
            "ADJ": 2,
            "CCONJ": 6,
            "NON-ZH": 1,
            "DET": 3,
            "NUM": 1
        },
        "tag_counts": {
            "P": 5,
            "NR": 1,
            "PU": 11,
            "NN": 31,
            "AD": 12,
            "VV": 10,
            "DEC": 2,
            "VC": 1,
            "JJ": 2,
            "CC": 6,
            "NON-ZH": 1,
            "DEG": 4,
            "DT": 3,
            "VA": 4,
            "LC": 1,
            "CD": 1,
            "AS": 1
        }
    },
    {
        "response_id": "p7-r13",
        "pos_counts": {
            "ADP": 6,
            "PROPN": 2,
            "PUNCT": 16,
            "NOUN": 36,
            "PART": 10,
            "ADV": 10,
            "VERB": 15,
            "CCONJ": 6,
            "ADJ": 5,
            "NON-ZH": 1,
            "DET": 2,
            "NUM": 1,
            "X": 1
        },
        "tag_counts": {
            "P": 6,
            "NR": 2,
            "PU": 16,
            "NN": 36,
            "DEG": 6,
            "AD": 10,
            "VA": 4,
            "VC": 2,
            "CC": 6,
            "JJ": 5,
            "NON-ZH": 1,
            "VV": 9,
            "AS": 1,
            "DEC": 2,
            "DT": 2,
            "CD": 1,
            "LC": 1,
            "SB": 1
        }
    },
    {
        "response_id": "p7-r14",
        "pos_counts": {
            "ADP": 3,
            "PROPN": 2,
            "PUNCT": 12,
            "NOUN": 34,
            "ADV": 11,
            "VERB": 15,
            "PART": 11,
            "ADJ": 6,
            "CCONJ": 3,
            "NON-ZH": 1,
            "DET": 1
        },
        "tag_counts": {
            "P": 3,
            "NR": 2,
            "PU": 12,
            "NN": 34,
            "AD": 11,
            "VV": 12,
            "DEC": 2,
            "VC": 1,
            "JJ": 6,
            "DEG": 6,
            "CC": 3,
            "NON-ZH": 1,
            "DT": 1,
            "AS": 2,
            "VA": 2,
            "MSP": 1
        }
    },
    {
        "response_id": "p7-r15",
        "pos_counts": {
            "ADP": 5,
            "PROPN": 3,
            "PUNCT": 16,
            "NOUN": 40,
            "CCONJ": 6,
            "ADJ": 3,
            "ADV": 10,
            "NON-ZH": 1,
            "VERB": 19,
            "DET": 3,
            "PART": 6,
            "NUM": 1,
            "PRON": 2
        },
        "tag_counts": {
            "P": 5,
            "NR": 3,
            "PU": 16,
            "NN": 40,
            "CC": 6,
            "JJ": 3,
            "AD": 10,
            "NON-ZH": 1,
            "VV": 16,
            "VC": 1,
            "DT": 3,
            "AS": 2,
            "VA": 2,
            "DEG": 3,
            "CD": 1,
            "LC": 1,
            "PN": 2
        }
    },
    {
        "response_id": "p7-r16",
        "pos_counts": {
            "ADP": 4,
            "PROPN": 2,
            "PUNCT": 11,
            "NOUN": 32,
            "ADV": 10,
            "VERB": 14,
            "PART": 9,
            "CCONJ": 7,
            "ADJ": 3,
            "NON-ZH": 1,
            "DET": 2,
            "NUM": 3,
            "X": 1,
            "PRON": 1
        },
        "tag_counts": {
            "P": 4,
            "NR": 2,
            "PU": 11,
            "NN": 32,
            "AD": 10,
            "VV": 9,
            "DEC": 2,
            "VC": 1,
            "CC": 7,
            "JJ": 3,
            "DEG": 5,
            "NON-ZH": 1,
            "DT": 2,
            "AS": 1,
            "VA": 4,
            "CD": 2,
            "SB": 1,
            "M": 1,
            "PN": 1,
            "LC": 1
        }
    },
    {
        "response_id": "p7-r17",
        "pos_counts": {
            "ADP": 3,
            "PROPN": 2,
            "PUNCT": 12,
            "NOUN": 29,
            "ADV": 15,
            "VERB": 13,
            "PART": 9,
            "ADJ": 3,
            "CCONJ": 3,
            "NON-ZH": 1,
            "DET": 1
        },
        "tag_counts": {
            "P": 3,
            "NR": 2,
            "PU": 12,
            "NN": 29,
            "AD": 15,
            "VA": 4,
            "DEC": 2,
            "VC": 1,
            "DEG": 4,
            "JJ": 3,
            "CC": 3,
            "NON-ZH": 1,
            "DT": 1,
            "VV": 8,
            "AS": 2,
            "LC": 1
        }
    },
    {
        "response_id": "p7-r18",
        "pos_counts": {
            "ADP": 6,
            "PROPN": 1,
            "PUNCT": 11,
            "NOUN": 31,
            "ADV": 15,
            "VERB": 13,
            "PART": 11,
            "CCONJ": 3,
            "NON-ZH": 1,
            "DET": 2,
            "ADJ": 2,
            "NUM": 1,
            "PRON": 1
        },
        "tag_counts": {
            "P": 6,
            "NR": 1,
            "PU": 11,
            "NN": 31,
            "AD": 15,
            "VA": 3,
            "DEC": 2,
            "VC": 1,
            "DEG": 6,
            "CC": 3,
            "NON-ZH": 1,
            "DT": 2,
            "VV": 9,
            "AS": 2,
            "JJ": 2,
            "CD": 1,
            "PN": 1,
            "LC": 1
        }
    },
    {
        "response_id": "p7-r19",
        "pos_counts": {
            "ADP": 2,
            "PROPN": 1,
            "PUNCT": 12,
            "NOUN": 31,
            "ADV": 9,
            "VERB": 15,
            "PART": 8,
            "ADJ": 5,
            "CCONJ": 5,
            "NON-ZH": 1,
            "DET": 3,
            "NUM": 1
        },
        "tag_counts": {
            "P": 2,
            "NR": 1,
            "PU": 12,
            "NN": 31,
            "AD": 9,
            "VV": 12,
            "DEC": 3,
            "JJ": 5,
            "VC": 1,
            "DEG": 3,
            "CC": 5,
            "NON-ZH": 1,
            "DT": 3,
            "AS": 2,
            "VA": 2,
            "CD": 1
        }
    },
    {
        "response_id": "p7-r20",
        "pos_counts": {
            "ADP": 5,
            "PROPN": 1,
            "PUNCT": 11,
            "NOUN": 32,
            "PART": 10,
            "ADV": 12,
            "VERB": 15,
            "ADJ": 3,
            "CCONJ": 4,
            "NON-ZH": 1,
            "DET": 2,
            "PRON": 2,
            "X": 1,
            "NUM": 1
        },
        "tag_counts": {
            "P": 5,
            "NR": 1,
            "PU": 11,
            "NN": 32,
            "DEG": 5,
            "AD": 12,
            "VA": 3,
            "VC": 1,
            "JJ": 3,
            "CC": 4,
            "NON-ZH": 1,
            "DT": 2,
            "VV": 11,
            "AS": 3,
            "DEC": 1,
            "PN": 2,
            "LC": 1,
            "SB": 1,
            "CD": 1
        }
    },
    {
        "response_id": "p7-r21",
        "pos_counts": {
            "ADP": 3,
            "PROPN": 2,
            "PUNCT": 12,
            "NOUN": 29,
            "PART": 10,
            "ADV": 13,
            "VERB": 16,
            "CCONJ": 3,
            "ADJ": 5,
            "NON-ZH": 1,
            "DET": 3,
            "X": 1
        },
        "tag_counts": {
            "P": 3,
            "NR": 2,
            "PU": 12,
            "NN": 29,
            "DEG": 4,
            "AD": 13,
            "VA": 3,
            "VC": 1,
            "CC": 3,
            "JJ": 5,
            "NON-ZH": 1,
            "ETC": 1,
            "DT": 3,
            "VV": 12,
            "AS": 3,
            "DEC": 1,
            "LC": 1,
            "SB": 1
        }
    },
    {
        "response_id": "p7-r22",
        "pos_counts": {
            "ADP": 4,
            "PROPN": 2,
            "PUNCT": 11,
            "NOUN": 28,
            "PART": 10,
            "VERB": 16,
            "ADV": 13,
            "CCONJ": 5,
            "ADJ": 6,
            "NON-ZH": 1,
            "PRON": 1,
            "DET": 1,
            "X": 1,
            "NUM": 2
        },
        "tag_counts": {
            "P": 4,
            "NR": 2,
            "PU": 11,
            "NN": 28,
            "DEG": 3,
            "VV": 8,
            "AD": 13,
            "VA": 6,
            "VC": 2,
            "CC": 5,
            "JJ": 6,
            "NON-ZH": 1,
            "ETC": 1,
            "PN": 1,
            "AS": 1,
            "DEC": 2,
            "DT": 1,
            "MSP": 1,
            "SB": 1,
            "CD": 1,
            "M": 1,
            "LC": 1,
            "DER": 1
        }
    },
    {
        "response_id": "p7-r23",
        "pos_counts": {
            "ADP": 6,
            "PROPN": 3,
            "PUNCT": 13,
            "NOUN": 32,
            "PART": 9,
            "ADV": 11,
            "VERB": 17,
            "CCONJ": 3,
            "ADJ": 3,
            "NON-ZH": 1,
            "DET": 1,
            "X": 2,
            "NUM": 1
        },
        "tag_counts": {
            "P": 6,
            "NR": 3,
            "PU": 13,
            "NN": 32,
            "DEG": 3,
            "AD": 11,
            "VA": 4,
            "VC": 1,
            "CC": 3,
            "JJ": 3,
            "NON-ZH": 1,
            "VV": 12,
            "AS": 2,
            "DEC": 3,
            "DT": 1,
            "SB": 2,
            "CD": 1,
            "LC": 1
        }
    },
    {
        "response_id": "p7-r24",
        "pos_counts": {
            "ADP": 3,
            "PROPN": 2,
            "PUNCT": 12,
            "NOUN": 31,
            "ADV": 16,
            "VERB": 17,
            "PART": 9,
            "CCONJ": 3,
            "NON-ZH": 1,
            "DET": 3,
            "ADJ": 5,
            "X": 1
        },
        "tag_counts": {
            "P": 3,
            "NR": 2,
            "PU": 12,
            "NN": 31,
            "AD": 16,
            "VV": 13,
            "DEC": 3,
            "VC": 1,
            "DEG": 4,
            "CC": 3,
            "NON-ZH": 1,
            "DT": 3,
            "AS": 2,
            "VA": 3,
            "JJ": 5,
            "SB": 1
        }
    },
    {
        "response_id": "p7-r25",
        "pos_counts": {
            "ADP": 5,
            "PROPN": 1,
            "PUNCT": 12,
            "NOUN": 33,
            "ADV": 9,
            "VERB": 12,
            "CCONJ": 6,
            "ADJ": 3,
            "NON-ZH": 1,
            "PART": 6,
            "DET": 3,
            "NUM": 1,
            "PRON": 2
        },
        "tag_counts": {
            "P": 5,
            "NR": 1,
            "PU": 12,
            "NN": 33,
            "AD": 9,
            "VV": 10,
            "VC": 1,
            "CC": 6,
            "JJ": 3,
            "NON-ZH": 1,
            "DEG": 3,
            "DT": 3,
            "AS": 2,
            "VA": 1,
            "LC": 1,
            "CD": 1,
            "PN": 2
        }
    },
    {
        "response_id": "p7-r26",
        "pos_counts": {
            "ADP": 5,
            "PROPN": 1,
            "PUNCT": 15,
            "NOUN": 36,
            "ADV": 15,
            "VERB": 14,
            "PART": 11,
            "ADJ": 2,
            "CCONJ": 3,
            "NON-ZH": 1,
            "DET": 3,
            "SCONJ": 1,
            "PRON": 1,
            "X": 1
        },
        "tag_counts": {
            "P": 5,
            "NR": 1,
            "PU": 15,
            "NN": 36,
            "AD": 15,
            "VA": 4,
            "DEC": 2,
            "VC": 1,
            "JJ": 2,
            "DEG": 4,
            "CC": 3,
            "NON-ZH": 1,
            "DT": 3,
            "VV": 9,
            "AS": 2,
            "LC": 2,
            "CS": 1,
            "PN": 1,
            "LB": 1,
            "MSP": 1
        }
    },
    {
        "response_id": "p7-r27",
        "pos_counts": {
            "ADP": 2,
            "PROPN": 2,
            "PUNCT": 15,
            "NOUN": 36,
            "PART": 10,
            "ADV": 12,
            "VERB": 17,
            "CCONJ": 4,
            "ADJ": 5,
            "PRON": 1,
            "NON-ZH": 1,
            "DET": 1,
            "NUM": 1
        },
        "tag_counts": {
            "P": 2,
            "NR": 2,
            "PU": 15,
            "NN": 36,
            "DEG": 5,
            "AD": 12,
            "VV": 14,
            "CC": 4,
            "JJ": 5,
            "PN": 1,
            "VC": 2,
            "NON-ZH": 1,
            "ETC": 1,
            "AS": 3,
            "VA": 1,
            "DT": 1,
            "LC": 1,
            "CD": 1
        }
    },
    {
        "response_id": "p7-r28",
        "pos_counts": {
            "ADP": 2,
            "PROPN": 2,
            "PUNCT": 16,
            "NOUN": 30,
            "ADV": 16,
            "VERB": 16,
            "ADJ": 4,
            "PART": 8,
            "CCONJ": 4,
            "NON-ZH": 1,
            "DET": 1,
            "NUM": 1
        },
        "tag_counts": {
            "P": 2,
            "NR": 2,
            "PU": 16,
            "NN": 30,
            "AD": 16,
            "VV": 10,
            "VC": 1,
            "JJ": 4,
            "DEG": 3,
            "CC": 4,
            "NON-ZH": 1,
            "ETC": 1,
            "DT": 1,
            "AS": 1,
            "DEC": 2,
            "VA": 5,
            "CD": 1,
            "MSP": 1
        }
    },
    {
        "response_id": "p7-r29",
        "pos_counts": {
            "NOUN": 34,
            "ADP": 3,
            "PROPN": 2,
            "ADV": 11,
            "VERB": 17,
            "PART": 8,
            "CCONJ": 4,
            "ADJ": 2,
            "PUNCT": 11,
            "NON-ZH": 1,
            "DET": 1,
            "NUM": 2,
            "PRON": 1
        },
        "tag_counts": {
            "NN": 34,
            "P": 3,
            "NR": 2,
            "AD": 11,
            "VV": 11,
            "DEC": 3,
            "VC": 1,
            "CC": 4,
            "JJ": 2,
            "DEG": 4,
            "PU": 11,
            "NON-ZH": 1,
            "DT": 1,
            "AS": 1,
            "VA": 5,
            "CD": 2,
            "PN": 1
        }
    },
    {
        "response_id": "p7-r30",
        "pos_counts": {
            "ADP": 7,
            "PROPN": 2,
            "PUNCT": 11,
            "NOUN": 35,
            "ADV": 8,
            "VERB": 13,
            "PART": 10,
            "ADJ": 4,
            "CCONJ": 3,
            "NON-ZH": 1,
            "DET": 3,
            "PRON": 1,
            "NUM": 1
        },
        "tag_counts": {
            "P": 7,
            "NR": 2,
            "PU": 11,
            "NN": 35,
            "AD": 8,
            "VA": 4,
            "DEC": 2,
            "JJ": 4,
            "VC": 1,
            "CC": 3,
            "NON-ZH": 1,
            "DEG": 5,
            "DT": 3,
            "VV": 8,
            "AS": 2,
            "PN": 1,
            "CD": 1,
            "LC": 1
        }
    },
    {
        "response_id": "p7-r31",
        "pos_counts": {
            "ADP": 6,
            "PROPN": 3,
            "PUNCT": 13,
            "NOUN": 36,
            "ADV": 14,
            "VERB": 13,
            "PART": 14,
            "CCONJ": 2,
            "NON-ZH": 1,
            "DET": 3,
            "ADJ": 2,
            "PRON": 1
        },
        "tag_counts": {
            "P": 6,
            "NR": 3,
            "PU": 13,
            "NN": 36,
            "AD": 14,
            "VA": 3,
            "DEC": 3,
            "VC": 2,
            "DEG": 5,
            "CC": 2,
            "NON-ZH": 1,
            "DT": 3,
            "VV": 8,
            "AS": 3,
            "LC": 3,
            "JJ": 2,
            "PN": 1
        }
    },
    {
        "response_id": "p7-r32",
        "pos_counts": {
            "ADP": 5,
            "PROPN": 2,
            "PUNCT": 12,
            "NOUN": 31,
            "CCONJ": 6,
            "ADJ": 3,
            "VERB": 16,
            "ADV": 10,
            "DET": 3,
            "PART": 9,
            "NON-ZH": 1,
            "PRON": 2
        },
        "tag_counts": {
            "P": 5,
            "NR": 2,
            "PU": 12,
            "NN": 31,
            "CC": 6,
            "JJ": 3,
            "VV": 11,
            "AD": 10,
            "VC": 1,
            "DT": 3,
            "AS": 2,
            "VA": 4,
            "DEC": 2,
            "NON-ZH": 1,
            "ETC": 1,
            "LC": 3,
            "PN": 2,
            "DEG": 1
        }
    },
    {
        "response_id": "p7-r33",
        "pos_counts": {
            "ADP": 2,
            "PROPN": 2,
            "PUNCT": 15,
            "NOUN": 35,
            "ADV": 12,
            "CCONJ": 7,
            "ADJ": 5,
            "NON-ZH": 1,
            "VERB": 16,
            "DET": 1,
            "PART": 8
        },
        "tag_counts": {
            "P": 2,
            "NR": 2,
            "PU": 15,
            "NN": 35,
            "AD": 12,
            "CC": 7,
            "JJ": 5,
            "NON-ZH": 1,
            "VV": 13,
            "DT": 1,
            "AS": 1,
            "VA": 3,
            "DEG": 5,
            "LC": 1,
            "DEC": 1
        }
    },
    {
        "response_id": "p7-r34",
        "pos_counts": {
            "ADP": 2,
            "PROPN": 1,
            "PUNCT": 10,
            "NOUN": 29,
            "ADV": 14,
            "VERB": 16,
            "PART": 7,
            "CCONJ": 5,
            "NON-ZH": 1,
            "DET": 2,
            "ADJ": 3,
            "NUM": 1
        },
        "tag_counts": {
            "P": 2,
            "NR": 1,
            "PU": 10,
            "NN": 29,
            "AD": 14,
            "VA": 5,
            "DEC": 2,
            "VC": 1,
            "DEG": 3,
            "CC": 5,
            "NON-ZH": 1,
            "DT": 2,
            "VV": 10,
            "AS": 1,
            "JJ": 3,
            "CD": 1,
            "MSP": 1
        }
    },
    {
        "response_id": "p7-r35",
        "pos_counts": {
            "ADP": 4,
            "PROPN": 2,
            "PUNCT": 13,
            "NOUN": 33,
            "CCONJ": 7,
            "ADJ": 5,
            "ADV": 11,
            "NON-ZH": 1,
            "VERB": 16,
            "DET": 1,
            "PART": 7,
            "NUM": 1,
            "PRON": 1
        },
        "tag_counts": {
            "P": 4,
            "NR": 2,
            "PU": 13,
            "NN": 33,
            "CC": 7,
            "JJ": 5,
            "AD": 11,
            "NON-ZH": 1,
            "VV": 11,
            "VC": 1,
            "DT": 1,
            "AS": 2,
            "DEC": 1,
            "VA": 4,
            "DEG": 4,
            "CD": 1,
            "PN": 1
        }
    },
    {
        "response_id": "p7-r36",
        "pos_counts": {
            "ADP": 3,
            "PROPN": 4,
            "PUNCT": 14,
            "NOUN": 34,
            "PART": 13,
            "VERB": 12,
            "ADJ": 6,
            "ADV": 9,
            "CCONJ": 5,
            "NON-ZH": 1,
            "NUM": 1,
            "X": 1,
            "PRON": 1,
            "DET": 1
        },
        "tag_counts": {
            "P": 3,
            "NR": 4,
            "PU": 14,
            "NN": 34,
            "DEG": 8,
            "VV": 10,
            "JJ": 6,
            "AD": 9,
            "CC": 5,
            "NON-ZH": 1,
            "AS": 3,
            "VA": 2,
            "DEC": 2,
            "CD": 1,
            "SB": 1,
            "PN": 1,
            "DT": 1
        }
    },
    {
        "response_id": "p7-r37",
        "pos_counts": {
            "ADP": 5,
            "PROPN": 2,
            "PUNCT": 14,
            "NOUN": 40,
            "PART": 11,
            "ADV": 14,
            "VERB": 15,
            "PRON": 1,
            "ADJ": 3,
            "CCONJ": 5,
            "NON-ZH": 1,
            "DET": 1,
            "X": 1,
            "NUM": 3
        },
        "tag_counts": {
            "P": 5,
            "NR": 2,
            "PU": 14,
            "NN": 40,
            "DEG": 5,
            "AD": 14,
            "VA": 6,
            "PN": 1,
            "VC": 1,
            "JJ": 3,
            "CC": 5,
            "NON-ZH": 1,
            "LC": 1,
            "VV": 8,
            "AS": 3,
            "DT": 1,
            "DEC": 2,
            "SB": 1,
            "CD": 2,
            "M": 1
        }
    },
    {
        "response_id": "p7-r38",
        "pos_counts": {
            "ADP": 4,
            "PROPN": 1,
            "PUNCT": 12,
            "NOUN": 31,
            "PART": 10,
            "VERB": 13,
            "DET": 2,
            "ADV": 12,
            "ADJ": 4,
            "CCONJ": 4,
            "NON-ZH": 1,
            "PRON": 1
        },
        "tag_counts": {
            "P": 4,
            "NR": 1,
            "PU": 12,
            "NN": 31,
            "DEG": 3,
            "VV": 8,
            "DT": 2,
            "AD": 12,
            "VC": 1,
            "JJ": 4,
            "CC": 4,
            "NON-ZH": 1,
            "AS": 3,
            "VA": 4,
            "DEC": 2,
            "PN": 1,
            "LC": 2
        }
    },
    {
        "response_id": "p7-r39",
        "pos_counts": {
            "ADP": 5,
            "PROPN": 2,
            "PUNCT": 12,
            "NOUN": 37,
            "PART": 9,
            "ADV": 9,
            "VERB": 15,
            "CCONJ": 5,
            "ADJ": 4,
            "NON-ZH": 1,
            "DET": 2,
            "PRON": 2,
            "X": 1
        },
        "tag_counts": {
            "P": 5,
            "NR": 2,
            "PU": 12,
            "NN": 37,
            "DEG": 6,
            "AD": 9,
            "VV": 12,
            "VC": 1,
            "CC": 5,
            "JJ": 4,
            "NON-ZH": 1,
            "DT": 2,
            "AS": 1,
            "PN": 2,
            "VA": 2,
            "LC": 2,
            "SB": 1
        }
    },
    {
        "response_id": "p7-r40",
        "pos_counts": {
            "ADP": 5,
            "PROPN": 2,
            "PUNCT": 11,
            "NOUN": 31,
            "ADV": 12,
            "VERB": 14,
            "PART": 10,
            "CCONJ": 3,
            "NON-ZH": 1,
            "DET": 4,
            "ADJ": 5
        },
        "tag_counts": {
            "P": 5,
            "NR": 2,
            "PU": 11,
            "NN": 31,
            "AD": 12,
            "VA": 2,
            "DEC": 2,
            "VC": 1,
            "DEG": 5,
            "CC": 3,
            "NON-ZH": 1,
            "DT": 4,
            "VV": 11,
            "AS": 2,
            "JJ": 5,
            "LC": 1
        }
    },
    {
        "response_id": "p7-r41",
        "pos_counts": {
            "ADP": 4,
            "PROPN": 1,
            "PUNCT": 15,
            "NOUN": 38,
            "PART": 13,
            "VERB": 18,
            "DET": 2,
            "ADV": 11,
            "CCONJ": 6,
            "NON-ZH": 2,
            "ADJ": 4,
            "PRON": 3,
            "X": 1,
            "NUM": 2
        },
        "tag_counts": {
            "P": 4,
            "NR": 1,
            "PU": 15,
            "NN": 38,
            "DEG": 5,
            "VV": 14,
            "DT": 2,
            "AD": 11,
            "VC": 2,
            "CC": 6,
            "NON-ZH": 2,
            "AS": 2,
            "VA": 2,
            "ETC": 2,
            "JJ": 4,
            "PN": 3,
            "LC": 2,
            "DEC": 2,
            "SB": 1,
            "CD": 1,
            "M": 1
        }
    },
    {
        "response_id": "p7-r42",
        "pos_counts": {
            "ADP": 5,
            "PROPN": 1,
            "PUNCT": 13,
            "NOUN": 34,
            "PART": 8,
            "VERB": 18,
            "ADV": 13,
            "CCONJ": 4,
            "ADJ": 8,
            "NON-ZH": 1,
            "DET": 2,
            "PRON": 1,
            "NUM": 1,
            "SCONJ": 1
        },
        "tag_counts": {
            "P": 5,
            "NR": 1,
            "PU": 13,
            "NN": 34,
            "DEG": 3,
            "VV": 11,
            "AD": 13,
            "VA": 5,
            "VC": 1,
            "CC": 4,
            "JJ": 8,
            "NON-ZH": 1,
            "ETC": 1,
            "DT": 2,
            "AS": 1,
            "DEC": 1,
            "PN": 1,
            "LC": 2,
            "CD": 1,
            "CS": 1,
            "VE": 1
        }
    },
    {
        "response_id": "p7-r43",
        "pos_counts": {
            "ADP": 4,
            "PROPN": 3,
            "PUNCT": 12,
            "NOUN": 32,
            "ADV": 16,
            "VERB": 14,
            "PART": 10,
            "CCONJ": 3,
            "NON-ZH": 1,
            "PRON": 1,
            "ADJ": 4,
            "DET": 1,
            "NUM": 1
        },
        "tag_counts": {
            "P": 4,
            "NR": 3,
            "PU": 12,
            "NN": 32,
            "AD": 16,
            "VV": 9,
            "DEC": 2,
            "VC": 1,
            "DEG": 6,
            "CC": 3,
            "NON-ZH": 1,
            "PN": 1,
            "AS": 2,
            "VA": 4,
            "JJ": 4,
            "DT": 1,
            "CD": 1
        }
    },
    {
        "response_id": "p7-r44",
        "pos_counts": {
            "ADP": 4,
            "PROPN": 2,
            "PUNCT": 11,
            "NOUN": 29,
            "ADV": 12,
            "VERB": 12,
            "CCONJ": 4,
            "ADJ": 3,
            "PART": 7,
            "NON-ZH": 1,
            "DET": 2,
            "NUM": 1
        },
        "tag_counts": {
            "P": 4,
            "NR": 2,
            "PU": 11,
            "NN": 29,
            "AD": 12,
            "VV": 8,
            "VC": 1,
            "CC": 4,
            "JJ": 3,
            "DEG": 4,
            "NON-ZH": 1,
            "DT": 2,
            "AS": 1,
            "VA": 3,
            "CD": 1,
            "LC": 2
        }
    },
    {
        "response_id": "p7-r45",
        "pos_counts": {
            "ADP": 3,
            "PROPN": 1,
            "PUNCT": 15,
            "NOUN": 30,
            "PART": 9,
            "ADV": 16,
            "VERB": 14,
            "CCONJ": 3,
            "NON-ZH": 1,
            "ADJ": 3,
            "DET": 1,
            "PRON": 3,
            "NUM": 1
        },
        "tag_counts": {
            "P": 3,
            "NR": 1,
            "PU": 15,
            "NN": 30,
            "DEG": 5,
            "AD": 16,
            "VA": 3,
            "VC": 2,
            "CC": 3,
            "NON-ZH": 1,
            "JJ": 3,
            "DT": 1,
            "VV": 9,
            "AS": 2,
            "DEC": 1,
            "PN": 3,
            "SP": 1,
            "CD": 1
        }
    },
    {
        "response_id": "p7-r46",
        "pos_counts": {
            "ADP": 3,
            "PROPN": 2,
            "PUNCT": 15,
            "NOUN": 36,
            "PART": 12,
            "ADV": 18,
            "VERB": 17,
            "CCONJ": 4,
            "NON-ZH": 1,
            "DET": 2,
            "ADJ": 4,
            "PRON": 1,
            "NUM": 1
        },
        "tag_counts": {
            "P": 3,
            "NR": 2,
            "PU": 15,
            "NN": 36,
            "DEG": 7,
            "AD": 18,
            "VA": 3,
            "VC": 1,
            "CC": 4,
            "NON-ZH": 1,
            "DT": 2,
            "VV": 13,
            "AS": 3,
            "JJ": 4,
            "PN": 1,
            "ETC": 2,
            "CD": 1
        }
    },
    {
        "response_id": "p7-r47",
        "pos_counts": {
            "ADP": 5,
            "PROPN": 1,
            "PUNCT": 14,
            "NOUN": 31,
            "ADV": 14,
            "VERB": 17,
            "PART": 7,
            "CCONJ": 5,
            "NON-ZH": 1,
            "PRON": 3,
            "ADJ": 3,
            "DET": 2,
            "NUM": 1
        },
        "tag_counts": {
            "P": 5,
            "NR": 1,
            "PU": 14,
            "NN": 31,
            "AD": 14,
            "VA": 5,
            "DEC": 1,
            "VC": 1,
            "DEG": 3,
            "CC": 5,
            "NON-ZH": 1,
            "PN": 3,
            "VV": 11,
            "AS": 2,
            "JJ": 3,
            "DT": 2,
            "CD": 1,
            "LC": 1
        }
    },
    {
        "response_id": "p7-r48",
        "pos_counts": {
            "ADP": 4,
            "PROPN": 1,
            "PUNCT": 12,
            "NOUN": 26,
            "ADV": 13,
            "ADJ": 7,
            "CCONJ": 3,
            "NON-ZH": 1,
            "VERB": 14,
            "DET": 2,
            "PART": 9,
            "PRON": 1
        },
        "tag_counts": {
            "P": 4,
            "NR": 1,
            "PU": 12,
            "NN": 26,
            "AD": 13,
            "JJ": 7,
            "CC": 3,
            "NON-ZH": 1,
            "VV": 11,
            "VC": 1,
            "DT": 2,
            "AS": 3,
            "DEC": 1,
            "ETC": 1,
            "DEG": 3,
            "PN": 1,
            "LC": 1,
            "VA": 2
        }
    },
    {
        "response_id": "p7-r49",
        "pos_counts": {
            "ADP": 3,
            "PROPN": 2,
            "PUNCT": 14,
            "NOUN": 28,
            "PART": 10,
            "ADV": 10,
            "VERB": 14,
            "CCONJ": 3,
            "ADJ": 4,
            "NON-ZH": 2,
            "DET": 1,
            "PRON": 2
        },
        "tag_counts": {
            "P": 3,
            "NR": 2,
            "PU": 14,
            "NN": 28,
            "DEG": 4,
            "AD": 10,
            "VA": 5,
            "VC": 1,
            "CC": 3,
            "JJ": 4,
            "NON-ZH": 2,
            "DT": 1,
            "VV": 8,
            "AS": 3,
            "ETC": 1,
            "DEC": 1,
            "PN": 2,
            "LC": 1
        }
    },
    {
        "response_id": "p7-r50",
        "pos_counts": {
            "ADP": 4,
            "PROPN": 2,
            "PUNCT": 10,
            "NOUN": 35,
            "ADV": 14,
            "VERB": 14,
            "PART": 12,
            "CCONJ": 7,
            "ADJ": 3,
            "NON-ZH": 1,
            "DET": 2,
            "X": 1
        },
        "tag_counts": {
            "P": 4,
            "NR": 2,
            "PU": 10,
            "NN": 35,
            "AD": 14,
            "VV": 8,
            "DEC": 2,
            "VC": 1,
            "CC": 7,
            "JJ": 3,
            "DEG": 6,
            "NON-ZH": 1,
            "ETC": 1,
            "DT": 2,
            "AS": 1,
            "VA": 5,
            "LC": 1,
            "LB": 1,
            "MSP": 1
        }
    },
    {
        "response_id": "p7-r51",
        "pos_counts": {
            "ADP": 3,
            "PROPN": 1,
            "PUNCT": 10,
            "NOUN": 28,
            "ADV": 12,
            "VERB": 12,
            "PART": 8,
            "CCONJ": 4,
            "ADJ": 5,
            "NON-ZH": 1,
            "DET": 1,
            "NUM": 1
        },
        "tag_counts": {
            "P": 3,
            "NR": 1,
            "PU": 10,
            "NN": 28,
            "AD": 12,
            "VA": 3,
            "DEC": 2,
            "VC": 1,
            "CC": 4,
            "JJ": 5,
            "DEG": 3,
            "NON-ZH": 1,
            "ETC": 1,
            "VV": 8,
            "AS": 2,
            "DT": 1,
            "CD": 1
        }
    },
    {
        "response_id": "p7-r52",
        "pos_counts": {
            "ADP": 3,
            "PROPN": 1,
            "PUNCT": 16,
            "NOUN": 31,
            "PART": 11,
            "ADV": 11,
            "DET": 2,
            "VERB": 15,
            "NON-ZH": 1,
            "PRON": 1,
            "CCONJ": 2,
            "ADJ": 5
        },
        "tag_counts": {
            "P": 3,
            "NR": 1,
            "PU": 16,
            "NN": 31,
            "DEG": 7,
            "AD": 11,
            "DT": 2,
            "VA": 3,
            "VC": 1,
            "NON-ZH": 1,
            "ETC": 2,
            "PN": 1,
            "VV": 11,
            "AS": 2,
            "CC": 2,
            "JJ": 5
        }
    },
    {
        "response_id": "p7-r53",
        "pos_counts": {
            "ADP": 4,
            "PROPN": 1,
            "PUNCT": 14,
            "NOUN": 29,
            "ADV": 15,
            "VERB": 16,
            "ADJ": 3,
            "CCONJ": 4,
            "NON-ZH": 1,
            "PART": 8,
            "DET": 3,
            "X": 1
        },
        "tag_counts": {
            "P": 4,
            "NR": 1,
            "PU": 14,
            "NN": 29,
            "AD": 15,
            "VA": 4,
            "VC": 1,
            "JJ": 3,
            "CC": 4,
            "NON-ZH": 1,
            "DEG": 2,
            "VV": 11,
            "DT": 3,
            "AS": 2,
            "DEC": 1,
            "LC": 2,
            "LB": 1,
            "MSP": 1
        }
    },
    {
        "response_id": "p7-r54",
        "pos_counts": {
            "ADP": 2,
            "PROPN": 1,
            "PUNCT": 12,
            "NOUN": 37,
            "ADV": 12,
            "VERB": 14,
            "PART": 6,
            "CCONJ": 5,
            "ADJ": 2,
            "NON-ZH": 1,
            "DET": 2,
            "NUM": 2
        },
        "tag_counts": {
            "P": 2,
            "NR": 1,
            "PU": 12,
            "NN": 37,
            "AD": 12,
            "VA": 5,
            "DEC": 3,
            "VV": 9,
            "CC": 5,
            "JJ": 2,
            "DEG": 2,
            "NON-ZH": 1,
            "DT": 2,
            "AS": 1,
            "CD": 2
        }
    },
    {
        "response_id": "p7-r55",
        "pos_counts": {
            "ADP": 3,
            "PROPN": 2,
            "PUNCT": 15,
            "NOUN": 37,
            "ADV": 19,
            "VERB": 15,
            "CCONJ": 3,
            "NON-ZH": 1,
            "PART": 10,
            "ADJ": 6,
            "DET": 2
        },
        "tag_counts": {
            "P": 3,
            "NR": 2,
            "PU": 15,
            "NN": 37,
            "AD": 19,
            "VV": 12,
            "VC": 1,
            "CC": 3,
            "NON-ZH": 1,
            "DEG": 4,
            "JJ": 6,
            "DT": 2,
            "AS": 4,
            "ETC": 1,
            "DEC": 1,
            "VA": 2
        }
    },
    {
        "response_id": "p7-r56",
        "pos_counts": {
            "ADP": 2,
            "PROPN": 2,
            "PUNCT": 15,
            "NOUN": 34,
            "CCONJ": 6,
            "DET": 4,
            "ADJ": 4,
            "ADV": 16,
            "NON-ZH": 1,
            "VERB": 17,
            "PART": 7
        },
        "tag_counts": {
            "P": 2,
            "NR": 2,
            "PU": 15,
            "NN": 34,
            "CC": 6,
            "DT": 4,
            "JJ": 4,
            "AD": 16,
            "NON-ZH": 1,
            "VV": 13,
            "VC": 1,
            "AS": 1,
            "DEC": 3,
            "DEG": 3,
            "VA": 3
        }
    },
    {
        "response_id": "p7-r57",
        "pos_counts": {
            "ADP": 5,
            "PROPN": 1,
            "PUNCT": 15,
            "NOUN": 33,
            "ADV": 18,
            "VERB": 19,
            "ADJ": 2,
            "PART": 10,
            "CCONJ": 5,
            "NON-ZH": 1,
            "DET": 2,
            "SCONJ": 1,
            "PRON": 1,
            "X": 1
        },
        "tag_counts": {
            "P": 5,
            "NR": 1,
            "PU": 15,
            "NN": 33,
            "AD": 18,
            "VA": 7,
            "VC": 1,
            "JJ": 2,
            "DEG": 4,
            "CC": 5,
            "NON-ZH": 1,
            "DT": 2,
            "VV": 11,
            "AS": 1,
            "DEC": 2,
            "LC": 2,
            "CS": 1,
            "PN": 1,
            "LB": 1,
            "MSP": 1
        }
    },
    {
        "response_id": "p7-r58",
        "pos_counts": {
            "ADP": 4,
            "PROPN": 3,
            "PUNCT": 13,
            "NOUN": 38,
            "CCONJ": 8,
            "DET": 2,
            "VERB": 13,
            "PART": 12,
            "ADV": 11,
            "ADJ": 5,
            "NON-ZH": 1,
            "NUM": 1,
            "X": 1
        },
        "tag_counts": {
            "P": 4,
            "NR": 3,
            "PU": 13,
            "NN": 38,
            "CC": 8,
            "DT": 2,
            "VV": 9,
            "DEC": 1,
            "AD": 11,
            "VC": 1,
            "JJ": 5,
            "DEG": 7,
            "NON-ZH": 1,
            "AS": 2,
            "VA": 3,
            "LC": 2,
            "CD": 1,
            "SB": 1
        }
    },
    {
        "response_id": "p7-r59",
        "pos_counts": {
            "ADP": 3,
            "PROPN": 2,
            "PUNCT": 14,
            "NOUN": 41,
            "PART": 13,
            "ADV": 12,
            "VERB": 16,
            "CCONJ": 5,
            "ADJ": 4,
            "NON-ZH": 1,
            "DET": 2
        },
        "tag_counts": {
            "P": 3,
            "NR": 2,
            "PU": 14,
            "NN": 41,
            "DEG": 8,
            "AD": 12,
            "VA": 4,
            "VC": 1,
            "CC": 5,
            "JJ": 4,
            "NON-ZH": 1,
            "ETC": 1,
            "VV": 11,
            "AS": 3,
            "DT": 2,
            "DEV": 1
        }
    },
    {
        "response_id": "p7-r60",
        "pos_counts": {
            "ADP": 3,
            "PROPN": 2,
            "PUNCT": 14,
            "NOUN": 23,
            "CCONJ": 5,
            "DET": 2,
            "ADJ": 4,
            "VERB": 20,
            "ADV": 13,
            "NON-ZH": 1,
            "PART": 5,
            "PRON": 2,
            "NUM": 1
        },
        "tag_counts": {
            "P": 3,
            "NR": 2,
            "PU": 14,
            "NN": 23,
            "CC": 5,
            "DT": 2,
            "JJ": 4,
            "VV": 14,
            "AD": 13,
            "VC": 1,
            "NON-ZH": 1,
            "AS": 2,
            "VA": 5,
            "DEC": 1,
            "PN": 2,
            "MSP": 1,
            "DEG": 1,
            "CD": 1
        }
    },
    {
        "response_id": "p7-r61",
        "pos_counts": {
            "ADP": 3,
            "PROPN": 3,
            "PUNCT": 12,
            "NOUN": 32,
            "ADV": 12,
            "VERB": 15,
            "PART": 10,
            "CCONJ": 5,
            "ADJ": 4,
            "NON-ZH": 1,
            "PRON": 1,
            "DET": 1,
            "NUM": 1
        },
        "tag_counts": {
            "P": 3,
            "NR": 3,
            "PU": 12,
            "NN": 32,
            "AD": 12,
            "VA": 2,
            "DEC": 3,
            "VC": 1,
            "CC": 5,
            "JJ": 4,
            "DEG": 3,
            "NON-ZH": 1,
            "PN": 1,
            "VV": 12,
            "AS": 2,
            "DT": 1,
            "ETC": 1,
            "CD": 1,
            "MSP": 1
        }
    },
    {
        "response_id": "p7-r62",
        "pos_counts": {
            "ADP": 3,
            "PROPN": 2,
            "PUNCT": 12,
            "NOUN": 35,
            "ADV": 12,
            "VERB": 17,
            "PART": 8,
            "CCONJ": 6,
            "ADJ": 6,
            "NON-ZH": 1,
            "DET": 2,
            "PRON": 2,
            "NUM": 1
        },
        "tag_counts": {
            "P": 3,
            "NR": 2,
            "PU": 12,
            "NN": 35,
            "AD": 12,
            "VA": 1,
            "DEC": 4,
            "VC": 2,
            "CC": 6,
            "JJ": 6,
            "DEG": 1,
            "NON-ZH": 1,
            "DT": 2,
            "VV": 14,
            "AS": 2,
            "PN": 2,
            "CD": 1,
            "MSP": 1
        }
    },
    {
        "response_id": "p7-r63",
        "pos_counts": {
            "ADP": 4,
            "PROPN": 1,
            "PUNCT": 14,
            "NOUN": 28,
            "CCONJ": 5,
            "ADJ": 4,
            "ADV": 7,
            "NON-ZH": 1,
            "VERB": 12,
            "DET": 2,
            "PART": 7
        },
        "tag_counts": {
            "P": 4,
            "NR": 1,
            "PU": 14,
            "NN": 28,
            "CC": 5,
            "JJ": 4,
            "AD": 7,
            "NON-ZH": 1,
            "VV": 9,
            "VC": 1,
            "DT": 2,
            "AS": 3,
            "VA": 2,
            "DEC": 1,
            "DEG": 2,
            "LC": 1
        }
    },
    {
        "response_id": "p7-r64",
        "pos_counts": {
            "ADP": 5,
            "PROPN": 2,
            "PUNCT": 11,
            "NOUN": 29,
            "ADV": 12,
            "VERB": 17,
            "PART": 9,
            "CCONJ": 5,
            "ADJ": 4,
            "NON-ZH": 1,
            "DET": 3,
            "PRON": 1
        },
        "tag_counts": {
            "P": 5,
            "NR": 2,
            "PU": 11,
            "NN": 29,
            "AD": 12,
            "VA": 4,
            "DEC": 3,
            "VC": 1,
            "CC": 5,
            "JJ": 4,
            "DEG": 3,
            "NON-ZH": 1,
            "DT": 3,
            "VV": 12,
            "AS": 2,
            "LC": 1,
            "PN": 1
        }
    },
    {
        "response_id": "p7-r65",
        "pos_counts": {
            "ADP": 6,
            "PROPN": 1,
            "PUNCT": 14,
            "NOUN": 30,
            "PART": 9,
            "ADV": 11,
            "VERB": 16,
            "CCONJ": 3,
            "ADJ": 5,
            "NON-ZH": 1,
            "DET": 1,
            "SCONJ": 1,
            "PRON": 2
        },
        "tag_counts": {
            "P": 6,
            "NR": 1,
            "PU": 14,
            "NN": 30,
            "DEG": 4,
            "AD": 11,
            "VV": 10,
            "VC": 1,
            "CC": 3,
            "JJ": 5,
            "NON-ZH": 1,
            "VA": 4,
            "DT": 1,
            "DEC": 1,
            "LC": 2,
            "CS": 1,
            "VE": 1,
            "MSP": 1,
            "PN": 2,
            "AS": 1
        }
    },
    {
        "response_id": "p7-r66",
        "pos_counts": {
            "ADP": 5,
            "PROPN": 2,
            "PUNCT": 13,
            "NOUN": 34,
            "ADV": 13,
            "VERB": 14,
            "PART": 10,
            "ADJ": 5,
            "CCONJ": 3,
            "NON-ZH": 1,
            "DET": 1,
            "NUM": 1
        },
        "tag_counts": {
            "P": 5,
            "NR": 2,
            "PU": 13,
            "NN": 34,
            "AD": 13,
            "VA": 3,
            "DEC": 2,
            "VC": 2,
            "JJ": 5,
            "CC": 3,
            "NON-ZH": 1,
            "VV": 9,
            "AS": 3,
            "DEG": 3,
            "DT": 1,
            "ETC": 1,
            "CD": 1,
            "LC": 1
        }
    },
    {
        "response_id": "p7-r67",
        "pos_counts": {
            "ADP": 4,
            "PROPN": 2,
            "PUNCT": 13,
            "NOUN": 28,
            "ADV": 13,
            "CCONJ": 4,
            "ADJ": 2,
            "NON-ZH": 1,
            "VERB": 18,
            "DET": 1,
            "PART": 7
        },
        "tag_counts": {
            "P": 4,
            "NR": 2,
            "PU": 13,
            "NN": 28,
            "AD": 13,
            "CC": 4,
            "JJ": 2,
            "NON-ZH": 1,
            "VV": 11,
            "VC": 1,
            "DT": 1,
            "AS": 3,
            "VA": 6,
            "DEC": 4
        }
    },
    {
        "response_id": "p7-r68",
        "pos_counts": {
            "ADP": 3,
            "PROPN": 2,
            "PUNCT": 11,
            "NOUN": 37,
            "PART": 11,
            "ADV": 13,
            "VERB": 13,
            "CCONJ": 5,
            "ADJ": 4,
            "NON-ZH": 1,
            "DET": 2
        },
        "tag_counts": {
            "P": 3,
            "NR": 2,
            "PU": 11,
            "NN": 37,
            "DEG": 7,
            "AD": 13,
            "VA": 4,
            "VC": 1,
            "CC": 5,
            "JJ": 4,
            "NON-ZH": 1,
            "ETC": 1,
            "DT": 2,
            "VV": 8,
            "AS": 1,
            "DEC": 1,
            "LC": 1
        }
    },
    {
        "response_id": "p7-r69",
        "pos_counts": {
            "ADP": 4,
            "PROPN": 1,
            "PUNCT": 12,
            "NOUN": 27,
            "PART": 8,
            "ADV": 12,
            "VERB": 17,
            "CCONJ": 4,
            "ADJ": 3,
            "NON-ZH": 1,
            "DET": 3,
            "X": 1,
            "NUM": 1
        },
        "tag_counts": {
            "P": 4,
            "NR": 1,
            "PU": 12,
            "NN": 27,
            "DEG": 3,
            "AD": 12,
            "VA": 4,
            "VC": 1,
            "CC": 4,
            "JJ": 3,
            "NON-ZH": 1,
            "DT": 3,
            "VV": 12,
            "AS": 2,
            "DEC": 1,
            "LC": 1,
            "SB": 1,
            "CD": 1,
            "MSP": 1
        }
    },
    {
        "response_id": "p7-r70",
        "pos_counts": {
            "ADP": 6,
            "PROPN": 2,
            "PUNCT": 13,
            "NOUN": 36,
            "ADV": 14,
            "VERB": 13,
            "PART": 8,
            "CCONJ": 7,
            "ADJ": 5,
            "NON-ZH": 1,
            "DET": 2,
            "SCONJ": 1
        },
        "tag_counts": {
            "P": 6,
            "NR": 2,
            "PU": 13,
            "NN": 36,
            "AD": 14,
            "VV": 8,
            "DEC": 3,
            "VC": 1,
            "CC": 7,
            "JJ": 5,
            "DEG": 2,
            "NON-ZH": 1,
            "DT": 2,
            "AS": 1,
            "VA": 4,
            "LC": 2,
            "CS": 1
        }
    },
    {
        "response_id": "p7-r71",
        "pos_counts": {
            "ADP": 5,
            "PROPN": 1,
            "PUNCT": 10,
            "NOUN": 30,
            "ADV": 13,
            "VERB": 15,
            "PART": 8,
            "CCONJ": 5,
            "ADJ": 2,
            "NON-ZH": 1,
            "DET": 3,
            "PRON": 1,
            "X": 1,
            "NUM": 1
        },
        "tag_counts": {
            "P": 5,
            "NR": 1,
            "PU": 10,
            "NN": 30,
            "AD": 13,
            "VA": 4,
            "DEC": 3,
            "VC": 1,
            "CC": 5,
            "JJ": 2,
            "DEG": 2,
            "NON-ZH": 1,
            "DT": 3,
            "VV": 10,
            "AS": 1,
            "PN": 1,
            "LC": 2,
            "SB": 1,
            "CD": 1
        }
    },
    {
        "response_id": "p7-r72",
        "pos_counts": {
            "NOUN": 27,
            "ADP": 4,
            "PROPN": 2,
            "ADV": 11,
            "VERB": 15,
            "PART": 7,
            "ADJ": 2,
            "PUNCT": 10,
            "CCONJ": 4,
            "NON-ZH": 1,
            "DET": 1,
            "NUM": 3,
            "X": 1
        },
        "tag_counts": {
            "NN": 27,
            "P": 4,
            "NR": 2,
            "AD": 11,
            "VV": 9,
            "DEC": 1,
            "VC": 1,
            "JJ": 2,
            "DEG": 3,
            "PU": 10,
            "CC": 4,
            "NON-ZH": 1,
            "DT": 1,
            "AS": 1,
            "VA": 5,
            "CD": 2,
            "MSP": 1,
            "SB": 1,
            "M": 1,
            "LC": 1
        }
    },
    {
        "response_id": "p7-r73",
        "pos_counts": {
            "ADP": 3,
            "PROPN": 1,
            "PUNCT": 14,
            "NOUN": 32,
            "PART": 13,
            "VERB": 20,
            "ADV": 15,
            "CCONJ": 7,
            "ADJ": 5,
            "NON-ZH": 1,
            "DET": 3,
            "X": 1,
            "PRON": 1
        },
        "tag_counts": {
            "P": 3,
            "NR": 1,
            "PU": 14,
            "NN": 32,
            "DEG": 4,
            "VV": 14,
            "AD": 15,
            "VA": 5,
            "VC": 1,
            "CC": 7,
            "JJ": 5,
            "NON-ZH": 1,
            "DT": 3,
            "AS": 3,
            "DEC": 3,
            "LC": 3,
            "SB": 1,
            "PN": 1
        }
    },
    {
        "response_id": "p7-r74",
        "pos_counts": {
            "ADP": 3,
            "PROPN": 1,
            "PUNCT": 13,
            "NOUN": 33,
            "ADV": 10,
            "ADJ": 3,
            "VERB": 16,
            "NON-ZH": 1,
            "PART": 8,
            "DET": 1,
            "CCONJ": 3
        },
        "tag_counts": {
            "P": 3,
            "NR": 1,
            "PU": 13,
            "NN": 33,
            "AD": 10,
            "JJ": 3,
            "VV": 8,
            "VC": 1,
            "NON-ZH": 1,
            "ETC": 2,
            "DT": 1,
            "AS": 2,
            "VA": 7,
            "DEC": 1,
            "CC": 3,
            "DEG": 2,
            "LC": 1
        }
    },
    {
        "response_id": "p7-r75",
        "pos_counts": {
            "ADP": 4,
            "PROPN": 1,
            "PUNCT": 10,
            "NOUN": 31,
            "ADV": 9,
            "VERB": 13,
            "PART": 9,
            "CCONJ": 5,
            "NON-ZH": 1,
            "DET": 2,
            "ADJ": 4,
            "NUM": 2,
            "PRON": 1,
            "X": 1
        },
        "tag_counts": {
            "P": 4,
            "NR": 1,
            "PU": 10,
            "NN": 31,
            "AD": 9,
            "VA": 3,
            "DEC": 2,
            "VC": 1,
            "DEG": 3,
            "CC": 5,
            "NON-ZH": 1,
            "DT": 2,
            "VV": 9,
            "AS": 2,
            "JJ": 4,
            "CD": 2,
            "MSP": 1,
            "PN": 1,
            "LC": 1,
            "SB": 1
        }
    },
    {
        "response_id": "p7-r76",
        "pos_counts": {
            "ADP": 3,
            "PROPN": 1,
            "PUNCT": 12,
            "NOUN": 32,
            "ADV": 12,
            "VERB": 14,
            "PART": 10,
            "CCONJ": 4,
            "ADJ": 5,
            "NON-ZH": 1,
            "DET": 1,
            "NUM": 3
        },
        "tag_counts": {
            "P": 3,
            "NR": 1,
            "PU": 12,
            "NN": 32,
            "AD": 12,
            "VA": 4,
            "DEC": 3,
            "VC": 1,
            "CC": 4,
            "JJ": 5,
            "DEG": 3,
            "NON-ZH": 1,
            "DT": 1,
            "VV": 9,
            "AS": 3,
            "CD": 2,
            "M": 1,
            "LC": 1
        }
    },
    {
        "response_id": "p7-r77",
        "pos_counts": {
            "ADP": 3,
            "PROPN": 2,
            "PUNCT": 12,
            "NOUN": 25,
            "CCONJ": 5,
            "DET": 2,
            "ADJ": 4,
            "VERB": 11,
            "ADV": 9,
            "NON-ZH": 1,
            "PART": 8,
            "X": 1
        },
        "tag_counts": {
            "P": 3,
            "NR": 2,
            "PU": 12,
            "NN": 25,
            "CC": 5,
            "DT": 2,
            "JJ": 4,
            "VV": 8,
            "AD": 9,
            "NON-ZH": 1,
            "AS": 3,
            "DEC": 2,
            "DEG": 2,
            "SB": 1,
            "VA": 3,
            "LC": 1
        }
    },
    {
        "response_id": "p7-r78",
        "pos_counts": {
            "ADP": 6,
            "PROPN": 2,
            "PUNCT": 11,
            "NOUN": 35,
            "ADV": 15,
            "VERB": 13,
            "PART": 10,
            "CCONJ": 6,
            "ADJ": 7,
            "NON-ZH": 1,
            "DET": 1,
            "PRON": 1,
            "NUM": 2
        },
        "tag_counts": {
            "P": 6,
            "NR": 2,
            "PU": 11,
            "NN": 35,
            "AD": 15,
            "VV": 10,
            "DEC": 2,
            "VC": 1,
            "CC": 6,
            "JJ": 7,
            "DEG": 6,
            "NON-ZH": 1,
            "DT": 1,
            "AS": 1,
            "VA": 2,
            "PN": 1,
            "LC": 1,
            "CD": 1,
            "M": 1
        }
    },
    {
        "response_id": "p7-r79",
        "pos_counts": {
            "ADP": 3,
            "PROPN": 2,
            "PUNCT": 9,
            "NOUN": 26,
            "ADV": 14,
            "VERB": 14,
            "PART": 8,
            "CCONJ": 2,
            "NON-ZH": 1,
            "DET": 2,
            "ADJ": 1
        },
        "tag_counts": {
            "P": 3,
            "NR": 2,
            "PU": 9,
            "NN": 26,
            "AD": 14,
            "VA": 3,
            "DEC": 2,
            "VC": 1,
            "DEG": 5,
            "CC": 2,
            "NON-ZH": 1,
            "DT": 2,
            "VV": 10,
            "AS": 1,
            "JJ": 1
        }
    },
    {
        "response_id": "p7-r80",
        "pos_counts": {
            "ADP": 4,
            "PROPN": 2,
            "PUNCT": 12,
            "NOUN": 32,
            "ADV": 14,
            "CCONJ": 5,
            "ADJ": 6,
            "NON-ZH": 1,
            "VERB": 10,
            "DET": 1,
            "PART": 5,
            "NUM": 1
        },
        "tag_counts": {
            "P": 4,
            "NR": 2,
            "PU": 12,
            "NN": 32,
            "AD": 14,
            "CC": 5,
            "JJ": 6,
            "NON-ZH": 1,
            "VV": 7,
            "VC": 1,
            "DT": 1,
            "AS": 1,
            "DEC": 1,
            "ETC": 1,
            "VA": 2,
            "DEG": 2,
            "CD": 1
        }
    },
    {
        "response_id": "p7-r81",
        "pos_counts": {
            "ADP": 4,
            "PROPN": 2,
            "PUNCT": 13,
            "NOUN": 36,
            "ADV": 17,
            "VERB": 15,
            "PART": 9,
            "CCONJ": 5,
            "NON-ZH": 1,
            "DET": 4,
            "ADJ": 2
        },
        "tag_counts": {
            "P": 4,
            "NR": 2,
            "PU": 13,
            "NN": 36,
            "AD": 17,
            "VA": 4,
            "DEC": 2,
            "VC": 1,
            "DEG": 5,
            "CC": 5,
            "NON-ZH": 1,
            "DT": 4,
            "VV": 10,
            "AS": 2,
            "JJ": 2
        }
    },
    {
        "response_id": "p7-r82",
        "pos_counts": {
            "ADP": 5,
            "PROPN": 2,
            "PUNCT": 12,
            "NOUN": 26,
            "PART": 10,
            "ADV": 12,
            "VERB": 18,
            "CCONJ": 4,
            "ADJ": 6,
            "NON-ZH": 1,
            "PRON": 2,
            "NUM": 1,
            "DET": 2,
            "X": 1
        },
        "tag_counts": {
            "P": 5,
            "NR": 2,
            "PU": 12,
            "NN": 26,
            "DEG": 5,
            "AD": 12,
            "VA": 5,
            "VC": 1,
            "CC": 4,
            "JJ": 6,
            "NON-ZH": 1,
            "PN": 2,
            "VV": 12,
            "AS": 2,
            "CD": 1,
            "DT": 2,
            "LC": 2,
            "ETC": 1,
            "SB": 1
        }
    },
    {
        "response_id": "p7-r83",
        "pos_counts": {
            "ADP": 4,
            "PROPN": 2,
            "PUNCT": 17,
            "NOUN": 44,
            "ADV": 14,
            "VERB": 21,
            "PART": 9,
            "ADJ": 8,
            "CCONJ": 6,
            "NON-ZH": 1,
            "DET": 1,
            "X": 1,
            "PRON": 1
        },
        "tag_counts": {
            "P": 4,
            "NR": 2,
            "PU": 17,
            "NN": 44,
            "AD": 14,
            "VV": 18,
            "DEC": 1,
            "VC": 1,
            "JJ": 8,
            "CC": 6,
            "NON-ZH": 1,
            "DEG": 5,
            "DT": 1,
            "LC": 3,
            "VA": 2,
            "SB": 1,
            "PN": 1
        }
    },
    {
        "response_id": "p7-r84",
        "pos_counts": {
            "ADP": 4,
            "PROPN": 3,
            "PUNCT": 12,
            "NOUN": 35,
            "ADV": 15,
            "VERB": 15,
            "PART": 10,
            "ADJ": 4,
            "CCONJ": 4,
            "NON-ZH": 1,
            "DET": 1,
            "X": 1,
            "PRON": 1
        },
        "tag_counts": {
            "P": 4,
            "NR": 3,
            "PU": 12,
            "NN": 35,
            "AD": 15,
            "VA": 4,
            "DEC": 1,
            "VC": 2,
            "JJ": 4,
            "DEG": 7,
            "CC": 4,
            "NON-ZH": 1,
            "DT": 1,
            "VV": 9,
            "AS": 2,
            "SB": 1,
            "PN": 1
        }
    },
    {
        "response_id": "p7-r85",
        "pos_counts": {
            "ADP": 4,
            "PROPN": 1,
            "PUNCT": 13,
            "NOUN": 34,
            "ADV": 11,
            "VERB": 15,
            "PART": 10,
            "CCONJ": 4,
            "ADJ": 6,
            "NON-ZH": 1,
            "DET": 2,
            "NUM": 1
        },
        "tag_counts": {
            "P": 4,
            "NR": 1,
            "PU": 13,
            "NN": 34,
            "AD": 11,
            "VV": 11,
            "DEC": 3,
            "VC": 1,
            "CC": 4,
            "JJ": 6,
            "DEG": 3,
            "NON-ZH": 1,
            "ETC": 1,
            "DT": 2,
            "AS": 2,
            "VA": 3,
            "LC": 1,
            "CD": 1
        }
    },
    {
        "response_id": "p7-r86",
        "pos_counts": {
            "ADP": 2,
            "PROPN": 2,
            "PUNCT": 11,
            "NOUN": 27,
            "ADV": 13,
            "VERB": 16,
            "PART": 6,
            "ADJ": 3,
            "CCONJ": 5,
            "NON-ZH": 1,
            "DET": 2,
            "NUM": 1,
            "PRON": 1
        },
        "tag_counts": {
            "P": 2,
            "NR": 2,
            "PU": 11,
            "NN": 27,
            "AD": 13,
            "VA": 4,
            "DEC": 2,
            "VC": 1,
            "VV": 11,
            "DEG": 2,
            "JJ": 3,
            "CC": 5,
            "NON-ZH": 1,
            "DT": 2,
            "AS": 2,
            "CD": 1,
            "PN": 1
        }
    },
    {
        "response_id": "p7-r87",
        "pos_counts": {
            "ADP": 5,
            "PROPN": 2,
            "PUNCT": 17,
            "NOUN": 42,
            "ADV": 12,
            "CCONJ": 6,
            "ADJ": 3,
            "NON-ZH": 1,
            "VERB": 20,
            "DET": 2,
            "PART": 13,
            "PRON": 2,
            "NUM": 1
        },
        "tag_counts": {
            "P": 5,
            "NR": 2,
            "PU": 17,
            "NN": 42,
            "AD": 12,
            "CC": 6,
            "JJ": 3,
            "NON-ZH": 1,
            "VV": 15,
            "VC": 1,
            "DT": 2,
            "AS": 5,
            "VA": 4,
            "DEC": 2,
            "PN": 2,
            "DEG": 5,
            "ETC": 1,
            "CD": 1
        }
    },
    {
        "response_id": "p7-r88",
        "pos_counts": {
            "ADP": 3,
            "PROPN": 1,
            "PUNCT": 11,
            "NOUN": 32,
            "PART": 6,
            "ADV": 9,
            "VERB": 15,
            "CCONJ": 7,
            "ADJ": 5,
            "NON-ZH": 1,
            "DET": 2,
            "PRON": 1,
            "NUM": 2,
            "X": 1
        },
        "tag_counts": {
            "P": 3,
            "NR": 1,
            "PU": 11,
            "NN": 32,
            "DEG": 3,
            "AD": 9,
            "VA": 2,
            "VC": 1,
            "CC": 7,
            "JJ": 5,
            "NON-ZH": 1,
            "ETC": 1,
            "DT": 2,
            "VV": 12,
            "AS": 1,
            "DEC": 1,
            "PN": 1,
            "CD": 2,
            "SB": 1
        }
    },
    {
        "response_id": "p7-r89",
        "pos_counts": {
            "ADP": 3,
            "PROPN": 1,
            "PUNCT": 16,
            "NOUN": 35,
            "ADV": 13,
            "ADJ": 9,
            "CCONJ": 3,
            "NON-ZH": 1,
            "VERB": 13,
            "DET": 2,
            "PART": 8,
            "PRON": 2,
            "SCONJ": 1
        },
        "tag_counts": {
            "P": 3,
            "NR": 1,
            "PU": 16,
            "NN": 35,
            "AD": 13,
            "JJ": 9,
            "CC": 3,
            "NON-ZH": 1,
            "VV": 10,
            "VC": 1,
            "DT": 2,
            "AS": 1,
            "DEC": 1,
            "VA": 2,
            "DEG": 5,
            "PN": 2,
            "CS": 1,
            "LC": 1
        }
    },
    {
        "response_id": "p7-r90",
        "pos_counts": {
            "ADP": 5,
            "PROPN": 1,
            "PUNCT": 13,
            "NOUN": 37,
            "ADV": 10,
            "VERB": 15,
            "PART": 10,
            "CCONJ": 5,
            "ADJ": 4,
            "NON-ZH": 1,
            "DET": 2,
            "X": 1,
            "PRON": 1
        },
        "tag_counts": {
            "P": 5,
            "NR": 1,
            "PU": 13,
            "NN": 37,
            "AD": 10,
            "VV": 11,
            "DEC": 3,
            "VC": 1,
            "CC": 5,
            "JJ": 4,
            "NON-ZH": 1,
            "LC": 2,
            "AS": 3,
            "DT": 2,
            "VA": 3,
            "DEG": 1,
            "SB": 1,
            "PN": 1,
            "MSP": 1
        }
    },
    {
        "response_id": "p7-r91",
        "pos_counts": {
            "ADP": 4,
            "PROPN": 1,
            "PUNCT": 15,
            "NOUN": 39,
            "ADV": 16,
            "VERB": 21,
            "PART": 10,
            "CCONJ": 7,
            "ADJ": 3,
            "NON-ZH": 1,
            "DET": 3,
            "NUM": 2
        },
        "tag_counts": {
            "P": 4,
            "NR": 1,
            "PU": 15,
            "NN": 39,
            "AD": 16,
            "VV": 15,
            "DEC": 3,
            "VC": 1,
            "CC": 7,
            "JJ": 3,
            "DEG": 4,
            "NON-ZH": 1,
            "DT": 3,
            "AS": 2,
            "VA": 5,
            "LC": 1,
            "CD": 2
        }
    },
    {
        "response_id": "p7-r92",
        "pos_counts": {
            "ADP": 2,
            "PROPN": 2,
            "PUNCT": 11,
            "NOUN": 28,
            "PART": 10,
            "ADV": 12,
            "VERB": 14,
            "ADJ": 2,
            "CCONJ": 5,
            "NON-ZH": 1,
            "DET": 2,
            "NUM": 1
        },
        "tag_counts": {
            "P": 2,
            "NR": 2,
            "PU": 11,
            "NN": 28,
            "DEG": 6,
            "AD": 12,
            "VA": 5,
            "VC": 1,
            "JJ": 2,
            "CC": 5,
            "NON-ZH": 1,
            "ETC": 1,
            "DT": 2,
            "VV": 8,
            "AS": 3,
            "CD": 1
        }
    },
    {
        "response_id": "p7-r93",
        "pos_counts": {
            "NOUN": 35,
            "ADP": 4,
            "PROPN": 2,
            "ADV": 12,
            "VERB": 15,
            "PART": 9,
            "ADJ": 4,
            "PUNCT": 11,
            "CCONJ": 4,
            "NON-ZH": 1,
            "DET": 2,
            "X": 1
        },
        "tag_counts": {
            "NN": 35,
            "P": 4,
            "NR": 2,
            "AD": 12,
            "VV": 11,
            "DEC": 3,
            "VC": 1,
            "JJ": 4,
            "DEG": 3,
            "PU": 11,
            "CC": 4,
            "NON-ZH": 1,
            "DT": 2,
            "AS": 2,
            "VA": 3,
            "SB": 1,
            "LC": 1
        }
    },
    {
        "response_id": "p7-r94",
        "pos_counts": {
            "ADP": 4,
            "PROPN": 2,
            "PUNCT": 13,
            "NOUN": 33,
            "ADV": 11,
            "VERB": 13,
            "PART": 8,
            "CCONJ": 4,
            "ADJ": 5,
            "NON-ZH": 1,
            "DET": 2,
            "PRON": 1,
            "NUM": 1
        },
        "tag_counts": {
            "P": 4,
            "NR": 2,
            "PU": 13,
            "NN": 33,
            "AD": 11,
            "VV": 10,
            "DEC": 2,
            "VC": 1,
            "CC": 4,
            "JJ": 5,
            "DEG": 3,
            "NON-ZH": 1,
            "DT": 2,
            "AS": 2,
            "PN": 1,
            "ETC": 1,
            "VA": 2,
            "CD": 1
        }
    },
    {
        "response_id": "p7-r95",
        "pos_counts": {
            "ADP": 4,
            "PROPN": 2,
            "PUNCT": 14,
            "NOUN": 32,
            "PART": 8,
            "ADV": 13,
            "VERB": 17,
            "CCONJ": 4,
            "ADJ": 5,
            "NON-ZH": 1,
            "PRON": 4,
            "DET": 1,
            "X": 1
        },
        "tag_counts": {
            "P": 4,
            "NR": 2,
            "PU": 14,
            "NN": 32,
            "DEG": 4,
            "AD": 13,
            "VA": 5,
            "VC": 2,
            "CC": 4,
            "JJ": 5,
            "NON-ZH": 1,
            "PN": 4,
            "VV": 9,
            "AS": 1,
            "DT": 1,
            "MSP": 1,
            "VE": 1,
            "SP": 1,
            "DEC": 1,
            "SB": 1
        }
    },
    {
        "response_id": "p7-r96",
        "pos_counts": {
            "NOUN": 26,
            "ADP": 4,
            "PROPN": 1,
            "ADV": 11,
            "VERB": 12,
            "PART": 11,
            "ADJ": 5,
            "PUNCT": 12,
            "CCONJ": 2,
            "NON-ZH": 1,
            "DET": 2,
            "NUM": 1,
            "PRON": 1,
            "X": 1
        },
        "tag_counts": {
            "NN": 26,
            "P": 4,
            "NR": 1,
            "AD": 11,
            "VV": 9,
            "DEC": 2,
            "VC": 1,
            "JJ": 5,
            "PU": 12,
            "CC": 2,
            "NON-ZH": 1,
            "DEG": 3,
            "DT": 2,
            "AS": 3,
            "VA": 2,
            "ETC": 1,
            "CD": 1,
            "LC": 2,
            "PN": 1,
            "SB": 1
        }
    },
    {
        "response_id": "p7-r97",
        "pos_counts": {
            "ADP": 3,
            "PROPN": 1,
            "PUNCT": 13,
            "NOUN": 31,
            "PART": 7,
            "VERB": 15,
            "ADV": 16,
            "CCONJ": 4,
            "ADJ": 4,
            "NON-ZH": 1,
            "DET": 1,
            "X": 1,
            "NUM": 1
        },
        "tag_counts": {
            "P": 3,
            "NR": 1,
            "PU": 13,
            "NN": 31,
            "DEG": 3,
            "VV": 9,
            "AD": 16,
            "VA": 5,
            "VC": 1,
            "CC": 4,
            "JJ": 4,
            "NON-ZH": 1,
            "DT": 1,
            "AS": 2,
            "DEC": 2,
            "SB": 1,
            "CD": 1
        }
    },
    {
        "response_id": "p7-r98",
        "pos_counts": {
            "ADP": 5,
            "PROPN": 1,
            "PUNCT": 11,
            "NOUN": 34,
            "ADV": 11,
            "VERB": 13,
            "PART": 8,
            "ADJ": 4,
            "CCONJ": 5,
            "NON-ZH": 1,
            "DET": 2,
            "NUM": 1
        },
        "tag_counts": {
            "P": 5,
            "NR": 1,
            "PU": 11,
            "NN": 34,
            "AD": 11,
            "VV": 10,
            "DEC": 2,
            "VC": 1,
            "JJ": 4,
            "DEG": 4,
            "CC": 5,
            "NON-ZH": 1,
            "DT": 2,
            "AS": 1,
            "VA": 2,
            "LC": 1,
            "CD": 1
        }
    },
    {
        "response_id": "p7-r99",
        "pos_counts": {
            "ADP": 4,
            "PROPN": 4,
            "PUNCT": 13,
            "NOUN": 37,
            "ADV": 14,
            "VERB": 15,
            "PART": 9,
            "CCONJ": 5,
            "ADJ": 5,
            "NON-ZH": 1,
            "DET": 3,
            "NUM": 1
        },
        "tag_counts": {
            "P": 4,
            "NR": 4,
            "PU": 13,
            "NN": 37,
            "AD": 14,
            "VV": 13,
            "DEC": 1,
            "VC": 1,
            "CC": 5,
            "JJ": 5,
            "DEG": 7,
            "NON-ZH": 1,
            "DT": 3,
            "AS": 1,
            "VA": 1,
            "CD": 1
        }
    },
    {
        "response_id": "p7-r100",
        "pos_counts": {
            "ADP": 4,
            "PROPN": 1,
            "PUNCT": 12,
            "NOUN": 34,
            "ADV": 12,
            "VERB": 16,
            "PART": 9,
            "ADJ": 3,
            "CCONJ": 6,
            "NON-ZH": 1,
            "DET": 2,
            "NUM": 1
        },
        "tag_counts": {
            "P": 4,
            "NR": 1,
            "PU": 12,
            "NN": 34,
            "AD": 12,
            "VA": 3,
            "DEC": 2,
            "VC": 1,
            "DEG": 3,
            "JJ": 3,
            "CC": 6,
            "NON-ZH": 1,
            "DT": 2,
            "VV": 12,
            "AS": 3,
            "CD": 1,
            "MSP": 1
        }
    }
]