{
    "pos_tag_counting_response_zh_zh_10": {
        "NOUN": {
            "mean": 0.3504,
            "std_dev": 0.0238,
            "cv": 6.8014
        },
        "PROPN": {
            "mean": 0.0025,
            "std_dev": 0.0051,
            "cv": 201.6158
        },
        "VERB": {
            "mean": 0.2181,
            "std_dev": 0.0252,
            "cv": 11.5726
        },
        "AUX": {
            "mean": 0.0,
            "std_dev": 0.0,
            "cv": 0
        },
        "ADJ": {
            "mean": 0.0133,
            "std_dev": 0.0103,
            "cv": 77.2176
        },
        "ADV": {
            "mean": 0.1059,
            "std_dev": 0.0186,
            "cv": 17.5558
        },
        "PRON": {
            "mean": 0.0017,
            "std_dev": 0.004,
            "cv": 231.0726
        },
        "NUM": {
            "mean": 0.0126,
            "std_dev": 0.0094,
            "cv": 74.2412
        },
        "DET": {
            "mean": 0.0098,
            "std_dev": 0.009,
            "cv": 92.311
        },
        "PART": {
            "mean": 0.0813,
            "std_dev": 0.0223,
            "cv": 27.4753
        },
        "CCONJ": {
            "mean": 0.0328,
            "std_dev": 0.0124,
            "cv": 37.6658
        },
        "SCONJ": {
            "mean": 0.0003,
            "std_dev": 0.0017,
            "cv": 569.2125
        },
        "ADP": {
            "mean": 0.0252,
            "std_dev": 0.0104,
            "cv": 41.0497
        },
        "INTJ": {
            "mean": 0.0,
            "std_dev": 0.0,
            "cv": 0
        },
        "PUNCT": {
            "mean": 0.1451,
            "std_dev": 0.0162,
            "cv": 11.1595
        },
        "X": {
            "mean": 0.0004,
            "std_dev": 0.0022,
            "cv": 492.3437
        },
        "NON-ZH": {
            "mean": 0.0004,
            "std_dev": 0.003,
            "cv": 700.0
        }
    }
}